[
  {
    "input": "in rage d+1+2",
    "hit_level": "m",
    "damage": "55",
    "startup": "20 pc8~17",
    "block": "-22",
    "hit": "Throw(KND)",
    "counter": "Throw(KND)",
    "note": "Rage art"
  },
  {
    "input": "in rage f+2+3",
    "hit_level": "m (TJ)",
    "damage": "50",
    "startup": "20~21 js5~17",
    "block": "+9~+10g (wl+15g)",
    "hit": "KND",
    "counter": "KND",
    "note": "Rage drive"
  },
  {
    "input": "in rage f+2+3, d/f",
    "hit_level": "m (TJ), (Special)",
    "damage": "50",
    "startup": "20~21",
    "block": "+28~+29?",
    "hit": "KND",
    "counter": "KND",
    "note": "Rage drive"
  },
  {
    "input": "1",
    "hit_level": "h",
    "damage": "7",
    "startup": "10",
    "block": "+1",
    "hit": "+8",
    "counter": "+8",
    "note": ""
  },
  {
    "input": "1, 2",
    "hit_level": "h, h",
    "damage": "7,10",
    "startup": "10,20",
    "block": "-1",
    "hit": "+5",
    "counter": "+5",
    "note": ""
  },
  {
    "input": "1, 2, u or D",
    "hit_level": "h, h, (Special)",
    "damage": "7,10",
    "startup": "10,20",
    "block": "0",
    "hit": "+6",
    "counter": "+6",
    "note": ""
  },
  {
    "input": "1, 2, 1",
    "hit_level": "h, h, h",
    "damage": "7,10,6",
    "startup": "10,20",
    "block": "-3",
    "hit": "+4",
    "counter": "+4",
    "note": ""
  },
  {
    "input": "1, 2, 1, 4",
    "hit_level": "h, h, h, l (TC)",
    "damage": "7,10,6,12",
    "startup": "s cs10~",
    "block": "-13",
    "hit": "-2",
    "counter": "-2",
    "note": ""
  },
  {
    "input": "1, 2, 3",
    "hit_level": "h, h, m",
    "damage": "7,10,15",
    "startup": " 10~",
    "block": "-13",
    "hit": "+2",
    "counter": "+2",
    "note": ""
  },
  {
    "input": "1, 2, 4",
    "hit_level": "h, h, h",
    "damage": "7,10,22",
    "startup": " 10~",
    "block": "-6",
    "hit": "KND",
    "counter": "CS",
    "note": "Tail spin"
  },
  {
    "input": "1, 2, 1+2",
    "hit_level": "h, h, m",
    "damage": "7,10,22",
    "startup": " 10~",
    "block": "-14",
    "hit": "KND",
    "counter": "KND",
    "note": ""
  },
  {
    "input": "1, 2, 1, 2",
    "hit_level": "h, h, h, h",
    "damage": "7,10,6,6",
    "startup": " 10~",
    "block": "-10",
    "hit": "+1",
    "counter": "+1",
    "note": ""
  },
  {
    "input": "1, 2, 1, 2, 1+2",
    "hit_level": "h, h, h, h, m",
    "damage": "7,10,6,6,22",
    "startup": " 10~",
    "block": "-14",
    "hit": "KND",
    "counter": "KND",
    "note": ""
  },
  {
    "input": "1, 4",
    "hit_level": "h, h",
    "damage": "7,17",
    "startup": " 10~",
    "block": "-4",
    "hit": "+1",
    "counter": "CS",
    "note": ""
  },
  {
    "input": "1, 4, 1",
    "hit_level": "h, h, m",
    "damage": "7,17,21",
    "startup": " 10~",
    "block": "-11~-10",
    "hit": "+15~+16kg",
    "counter": "KND",
    "note": "Tail spin"
  },
  {
    "input": "2",
    "hit_level": "h",
    "damage": "10",
    "startup": "10",
    "block": "+1",
    "hit": "+7",
    "counter": "+7",
    "note": ""
  },
  {
    "input": "2, 1",
    "hit_level": "h, h",
    "damage": "10,6",
    "startup": "10,26",
    "block": "-3",
    "hit": "+4",
    "counter": "+4",
    "note": ""
  },
  {
    "input": "2, 1, 4",
    "hit_level": "h, h, l (TC)",
    "damage": "10,6,12",
    "startup": "s cs10~",
    "block": "-13",
    "hit": "-2",
    "counter": "-2",
    "note": ""
  },
  {
    "input": "2, 3",
    "hit_level": "h, m",
    "damage": "10,15",
    "startup": " 10~",
    "block": "-13",
    "hit": "+2",
    "counter": "+2",
    "note": ""
  },
  {
    "input": "2, 4",
    "hit_level": "h, h",
    "damage": "10,22",
    "startup": " 10~",
    "block": "-6",
    "hit": "KND",
    "counter": "CS",
    "note": "Tail spin"
  },
  {
    "input": "2, 1+2",
    "hit_level": "h, m",
    "damage": "10,22",
    "startup": " 10~",
    "block": "-14",
    "hit": "KND",
    "counter": "KND",
    "note": ""
  },
  {
    "input": "3",
    "hit_level": "h",
    "damage": "14",
    "startup": "14",
    "block": "-16",
    "hit": "-5",
    "counter": "-5",
    "note": ""
  },
  {
    "input": "3, 3",
    "hit_level": "h, l (TC)",
    "damage": "14,10",
    "startup": "cs18~",
    "block": "-17",
    "hit": "-6",
    "counter": "-6",
    "note": ""
  },
  {
    "input": "3, 3, 2",
    "hit_level": "h, l (TC), m",
    "damage": "14,10,10",
    "startup": "18~",
    "block": "-13~-11",
    "hit": "Launch",
    "counter": "Launch",
    "note": ""
  },
  {
    "input": "3, 3, 4",
    "hit_level": "h, l (TC), h",
    "damage": "14,10,18",
    "startup": "18~",
    "block": "-6",
    "hit": "+5",
    "counter": "Launch",
    "note": ""
  },
  {
    "input": "3, 3, 4, 3",
    "hit_level": "h, l (TC), h, m",
    "damage": "14,10,18,20",
    "startup": "18~",
    "block": "+2~+3s",
    "hit": "+5~+6s",
    "counter": "KND",
    "note": ""
  },
  {
    "input": "3, 4",
    "hit_level": "h, h",
    "damage": "14,20",
    "startup": "18~",
    "block": "-6",
    "hit": "KND",
    "counter": "CS",
    "note": "Tail spin"
  },
  {
    "input": "3, d",
    "hit_level": "h, (Special)",
    "damage": "14",
    "startup": "14",
    "block": "-27",
    "hit": "-16",
    "counter": "-16",
    "note": ""
  },
  {
    "input": "3, d, D",
    "hit_level": "h, (Special)",
    "damage": "14",
    "startup": "14s",
    "block": "-23",
    "hit": "-12",
    "counter": "-12",
    "note": ""
  },
  {
    "input": "3, d, 1+2",
    "hit_level": "h, (Special), m",
    "damage": "14,22",
    "startup": "14",
    "block": "-11",
    "hit": "KND",
    "counter": "KND",
    "note": ""
  },
  {
    "input": "4",
    "hit_level": "h",
    "damage": "15",
    "startup": "11",
    "block": "-9",
    "hit": "+8",
    "counter": "Launch",
    "note": ""
  },
  {
    "input": "4, 3",
    "hit_level": "h, l (TC)",
    "damage": "15,13",
    "startup": "cs10~",
    "block": "-17",
    "hit": "-3",
    "counter": "-3",
    "note": ""
  },
  {
    "input": "4, 3, 2",
    "hit_level": "h, l (TC), m",
    "damage": "15,13,10",
    "startup": "10~",
    "block": "-13~-11",
    "hit": "Launch",
    "counter": "Launch",
    "note": ""
  },
  {
    "input": "4, 3, 4",
    "hit_level": "h, l (TC), h",
    "damage": "15,13,18",
    "startup": "10~",
    "block": "-6",
    "hit": "+5",
    "counter": "Launch",
    "note": ""
  },
  {
    "input": "4, 3, 4, 3",
    "hit_level": "h, l (TC), h, m",
    "damage": "15,13,10,20",
    "startup": "10~",
    "block": "+2~+3s",
    "hit": "+5~+6s",
    "counter": "JG",
    "note": ""
  },
  {
    "input": "4, u",
    "hit_level": "h, (Special)",
    "damage": "15",
    "startup": "11",
    "block": "-34",
    "hit": "-17",
    "counter": "Launch",
    "note": ""
  },
  {
    "input": "4, u, D",
    "hit_level": "h, (Special)",
    "damage": "15",
    "startup": "11s",
    "block": "-30",
    "hit": "-13",
    "counter": "Launch",
    "note": ""
  },
  {
    "input": "4, u, 1+2",
    "hit_level": "h, (Special), m",
    "damage": "15,22",
    "startup": "11",
    "block": "-11",
    "hit": "KND",
    "counter": "KND",
    "note": ""
  },
  {
    "input": "1+4",
    "hit_level": "mm",
    "damage": "4,20",
    "startup": "15~16, 28~29",
    "block": "-5~-4",
    "hit": "+4~+5s",
    "counter": "+6~+7s (+8s)",
    "note": ""
  },
  {
    "input": "f+2",
    "hit_level": "h",
    "damage": "12",
    "startup": "13",
    "block": "-3",
    "hit": "+8",
    "counter": "+8",
    "note": ""
  },
  {
    "input": "f+2, 1",
    "hit_level": "h, m",
    "damage": "12,12",
    "startup": "13",
    "block": "-13~-12",
    "hit": "-6~-5a",
    "counter": "-6~-5a",
    "note": ""
  },
  {
    "input": "f+2, 1, 2",
    "hit_level": "h, m, m",
    "damage": "12,12,20",
    "startup": "13",
    "block": "-12~-10s",
    "hit": "+4~+6s (KND)",
    "counter": "KND",
    "note": ""
  },
  {
    "input": "f+2, 1, 4",
    "hit_level": "h, m, h",
    "damage": "12,12,22",
    "startup": "13",
    "block": "-3~-1",
    "hit": "KND",
    "counter": "Tail spin",
    "note": "Tail spin"
  },
  {
    "input": "f+3",
    "hit_level": "hh",
    "damage": "10,20",
    "startup": "14~15, 25~26",
    "block": "+6~+7",
    "hit": "KND",
    "counter": "CS",
    "note": ""
  },
  {
    "input": "f+3 (Second hit ducked)",
    "hit_level": "h",
    "damage": "10",
    "startup": "14~15",
    "block": "-24s",
    "hit": "",
    "counter": "",
    "note": ""
  },
  {
    "input": "f+3 (Only first hit on counter)",
    "hit_level": "h",
    "damage": "10",
    "startup": "14~15",
    "block": "",
    "hit": "",
    "counter": "CS (12~13)",
    "note": ""
  },
  {
    "input": "f+4",
    "hit_level": "h",
    "damage": "14",
    "startup": "16",
    "block": "-12",
    "hit": "-3",
    "counter": "-1",
    "note": ""
  },
  {
    "input": "f+4, 3",
    "hit_level": "h, m",
    "damage": "14,13",
    "startup": "16",
    "block": "-14",
    "hit": "Launch",
    "counter": "Launch",
    "note": ""
  },
  {
    "input": "f+4, 3, 3",
    "hit_level": "h, m, m (TJ)",
    "damage": "14,13,20",
    "startup": "a js19~",
    "block": "-14~-11",
    "hit": "KND",
    "counter": "KND",
    "note": ""
  },
  {
    "input": "f+4, 4",
    "hit_level": "h, h",
    "damage": "14,17",
    "startup": " 19~",
    "block": "+1",
    "hit": "+13kg",
    "counter": "KND",
    "note": ""
  },
  {
    "input": "f+1+2 or WS+1+2",
    "hit_level": "m",
    "damage": "24",
    "startup": "17 pc8~16",
    "block": "-14",
    "hit": "KND",
    "counter": "KND",
    "note": "Power crush"
  },
  {
    "input": "d/f+1",
    "hit_level": "m",
    "damage": "13",
    "startup": "13~12",
    "block": "-1~0",
    "hit": "+5~+6",
    "counter": "+5~+6",
    "note": ""
  },
  {
    "input": "d/f+1, 2",
    "hit_level": "m, h",
    "damage": "13,10",
    "startup": "13,30",
    "block": "-3",
    "hit": "+2",
    "counter": "+9",
    "note": ""
  },
  {
    "input": "d/f+1, 2, f or d/f",
    "hit_level": "m, h, (Special)",
    "damage": "13,10",
    "startup": "13,30",
    "block": "-3",
    "hit": "+2",
    "counter": "+9",
    "note": ""
  },
  {
    "input": "d/f+1, 2, u or D",
    "hit_level": "m, h, (Special)",
    "damage": "13,10",
    "startup": "13,30",
    "block": "-1",
    "hit": "+4",
    "counter": "+11",
    "note": ""
  },
  {
    "input": "d/f+2",
    "hit_level": "m",
    "damage": "12",
    "startup": "15~16",
    "block": "-7~-6",
    "hit": "Launch(+4a)",
    "counter": "Launch",
    "note": ""
  },
  {
    "input": "d/f+3",
    "hit_level": "m",
    "damage": "13",
    "startup": "14",
    "block": "-11",
    "hit": "+1",
    "counter": "+1",
    "note": ""
  },
  {
    "input": "d/f+3, 1",
    "hit_level": "m, h",
    "damage": "13,10",
    "startup": "14",
    "block": "-8",
    "hit": "+3",
    "counter": "+3",
    "note": ""
  },
  {
    "input": "d/f+3, 1, d or u (Cancel)",
    "hit_level": "m, (Special)",
    "damage": "13",
    "startup": "14",
    "block": "-19",
    "hit": "-7",
    "counter": "-7",
    "note": ""
  },
  {
    "input": "d/f+3, 1, 2",
    "hit_level": "m, h, h",
    "damage": "13,10,6",
    "startup": "14",
    "block": "-10",
    "hit": "+1",
    "counter": "+1",
    "note": ""
  },
  {
    "input": "d/f+3, 1, 2, 1+2",
    "hit_level": "m, h, h, m",
    "damage": "13,10,6,22",
    "startup": "14",
    "block": "-14",
    "hit": "KND",
    "counter": "KND",
    "note": ""
  },
  {
    "input": "d/f+3, 2",
    "hit_level": "m, h",
    "damage": "13,12",
    "startup": "14,33",
    "block": "+1",
    "hit": "+5",
    "counter": "+12",
    "note": ""
  },
  {
    "input": "d/f+3, 2, f or d/f",
    "hit_level": "m, h, (Special)",
    "damage": "13,12",
    "startup": "14,33",
    "block": "-1",
    "hit": "+3",
    "counter": "+10",
    "note": ""
  },
  {
    "input": "d/f+3, 2, d or u",
    "hit_level": "m, h, (Special)",
    "damage": "13,12",
    "startup": "14,33",
    "block": "0",
    "hit": "+4",
    "counter": "+11",
    "note": ""
  },
  {
    "input": "d/f+3, 2, 1",
    "hit_level": "m, h, h",
    "damage": "13,12,6",
    "startup": "14,33",
    "block": "-3",
    "hit": "+4",
    "counter": "+4",
    "note": ""
  },
  {
    "input": "d/f+3, 2, 1, 4",
    "hit_level": "m, h, h, l (TC)",
    "damage": "13,12,6,12",
    "startup": "s cs10~",
    "block": "-13",
    "hit": "-2",
    "counter": "-2",
    "note": ""
  },
  {
    "input": "d/f+3, 2, 3",
    "hit_level": "m, h, m",
    "damage": "13,12,21",
    "startup": " 10~",
    "block": "-17~-16",
    "hit": "Launch",
    "counter": "Launch",
    "note": ""
  },
  {
    "input": "d/f+3, 2, 4",
    "hit_level": "m, h, h",
    "damage": "13,12,22",
    "startup": " 10~",
    "block": "-6",
    "hit": "KND",
    "counter": "CS",
    "note": "Tail spin"
  },
  {
    "input": "d/f+3, 2, d+3",
    "hit_level": "m, h, l (TC)",
    "damage": "13,12,10",
    "startup": "s cs10~",
    "block": "-14",
    "hit": "-3",
    "counter": "-3",
    "note": ""
  },
  {
    "input": "d/f+3, 2, d+3, 2",
    "hit_level": "m, h, l (TC), m",
    "damage": "13,12,10,10",
    "startup": " 10~",
    "block": "-13~-11",
    "hit": "Launch",
    "counter": "Launch",
    "note": ""
  },
  {
    "input": "d/f+3, 2, d+3, 4",
    "hit_level": "m, h, l (TC), h",
    "damage": "13,12,10,18",
    "startup": " 10~",
    "block": "-6",
    "hit": "+5",
    "counter": "Launch",
    "note": ""
  },
  {
    "input": "d/f+3, 2, d+3, 4 , 3",
    "hit_level": "m, h, l (TC), h, m",
    "damage": "13,12,10,18,20",
    "startup": " 10~",
    "block": "+2~+3s",
    "hit": "+5~+6s",
    "counter": "KND",
    "note": ""
  },
  {
    "input": "d/f+3, 3",
    "hit_level": "m, h",
    "damage": "13,6",
    "startup": " 10~",
    "block": "-14",
    "hit": "-3",
    "counter": "-3",
    "note": ""
  },
  {
    "input": "d/f+3, 3, 3",
    "hit_level": "m, h, h",
    "damage": "13,6",
    "startup": " 10~",
    "block": "-14",
    "hit": "-3",
    "counter": "-3",
    "note": ""
  },
  {
    "input": "d/f+3, 3, 3, 4",
    "hit_level": "m, h, h, h",
    "damage": "13,6,8,20",
    "startup": " 10~",
    "block": "-6",
    "hit": "KND",
    "counter": "CS",
    "note": "Tail spin"
  },
  {
    "input": "d/f+3, 4",
    "hit_level": "m, h (TJ)",
    "damage": "13,21",
    "startup": "a js20~",
    "block": "-4~-3",
    "hit": "+7~+8",
    "counter": "+7~+8",
    "note": ""
  },
  {
    "input": "d/f+3, 4, 4",
    "hit_level": "m, h (TJ), l",
    "damage": "13,21,20",
    "startup": "js1~11 cs15~",
    "block": "-13~-11",
    "hit": "KND",
    "counter": "KND",
    "note": ""
  },
  {
    "input": "d/f+3, 4, 3+4",
    "hit_level": "m, h (TJ), mm",
    "damage": "13,21,8,21",
    "startup": "js1~9, js28~41",
    "block": "-6~0",
    "hit": "KND",
    "counter": "KND",
    "note": ""
  },
  {
    "input": "d/f+3, f+4",
    "hit_level": "m, h",
    "damage": "13,20",
    "startup": "1~9, 28~41",
    "block": "-6",
    "hit": "KND",
    "counter": "CS",
    "note": "Tail spin"
  },
  {
    "input": "d/f+4",
    "hit_level": "m",
    "damage": "15",
    "startup": "12",
    "block": "-4",
    "hit": "+7",
    "counter": "+7",
    "note": ""
  },
  {
    "input": "d/f+1+2",
    "hit_level": "mm",
    "damage": "5,14",
    "startup": "16~17, 18~19",
    "block": "-3~-2",
    "hit": "+20~+21kg",
    "counter": "+20~+21kg",
    "note": ""
  },
  {
    "input": "d/f+1+2 (First hit only)",
    "hit_level": "m",
    "damage": "5",
    "startup": "16~17",
    "block": "-5~-4",
    "hit": "+7~+8",
    "counter": "+7~+8",
    "note": "Homing"
  },
  {
    "input": "d+1 or FC+1",
    "hit_level": "Sm",
    "damage": "5",
    "startup": "10s cs4~",
    "block": "-5",
    "hit": "+6",
    "counter": "+6",
    "note": ""
  },
  {
    "input": "d+1, 2 or FC+1, 2",
    "hit_level": "Sm (TC), Sm (TC)",
    "damage": "5,8",
    "startup": "s cs1~",
    "block": "-6",
    "hit": "+5",
    "counter": "+5",
    "note": ""
  },
  {
    "input": "d+1, 2, 4 or FC+1, 2, 4",
    "hit_level": "Sm (TC), Sm (TC), m",
    "damage": "5,8,10",
    "startup": " 1~",
    "block": "-14~-12",
    "hit": "-3~-1",
    "counter": "-3~-1",
    "note": ""
  },
  {
    "input": "d+1, n+4 or FC+1, n+4",
    "hit_level": "Sm (TC), m",
    "damage": "5,10",
    "startup": " 1~",
    "block": "-11~-10",
    "hit": "0~+1",
    "counter": "0~+1",
    "note": ""
  },
  {
    "input": "d+2",
    "hit_level": "l (TC)",
    "damage": "13",
    "startup": "20s cs6~",
    "block": "-12",
    "hit": "0",
    "counter": "+5",
    "note": ""
  },
  {
    "input": "d+2, 3",
    "hit_level": "l, h",
    "damage": "13,20",
    "startup": "20 6~",
    "block": "-6~-4",
    "hit": "KND",
    "counter": "CS",
    "note": "Tail spin"
  },
  {
    "input": "d+3 or FC+3",
    "hit_level": "l (TC)",
    "damage": "12",
    "startup": "16s cs4~",
    "block": "-17",
    "hit": "-3",
    "counter": "-3",
    "note": ""
  },
  {
    "input": "d+3, 2",
    "hit_level": "l (TC), m",
    "damage": "12,10",
    "startup": "16 4~",
    "block": "-13~-11",
    "hit": "Launch",
    "counter": "Launch",
    "note": ""
  },
  {
    "input": "d+3, 4",
    "hit_level": "l (TC), h",
    "damage": "12,18",
    "startup": "16 4~",
    "block": "-6",
    "hit": "+5",
    "counter": "Launch",
    "note": ""
  },
  {
    "input": "d+3, 4, 3",
    "hit_level": "l (TC), h, m",
    "damage": "12,18,20",
    "startup": "16 4~",
    "block": "+2~+3s",
    "hit": "+5~+6s",
    "counter": "KND",
    "note": ""
  },
  {
    "input": "d+4",
    "hit_level": "l (TC)",
    "damage": "7",
    "startup": "12s cs4~",
    "block": "-13",
    "hit": "-2",
    "counter": "-2",
    "note": ""
  },
  {
    "input": "FC+d/b or d+4 FC+D/F+4",
    "hit_level": "l (TC)",
    "damage": "10",
    "startup": "12s cs1~",
    "block": "-15",
    "hit": "-4",
    "counter": "-4",
    "note": ""
  },
  {
    "input": "d+4, 1",
    "hit_level": "l (TC), h",
    "damage": "7(10),10",
    "startup": "12 1~",
    "block": "0",
    "hit": "+6",
    "counter": "+11",
    "note": ""
  },
  {
    "input": "d+4, 1, d or u (Cancel)",
    "hit_level": "l (TC), (Special)",
    "damage": "7(10)",
    "startup": "12",
    "block": "-13(-15)",
    "hit": "-2(-4)",
    "counter": "-2(-4)",
    "note": ""
  },
  {
    "input": "d/b+2",
    "hit_level": "m",
    "damage": "20",
    "startup": "24~25",
    "block": "-5~-4",
    "hit": "KND",
    "counter": "KND",
    "note": "Tail spin, Homing"
  },
  {
    "input": "d/b+3",
    "hit_level": "l",
    "damage": "17",
    "startup": "20",
    "block": "-13",
    "hit": "+4s",
    "counter": "KND",
    "note": ""
  },
  {
    "input": "d/b+4",
    "hit_level": "l (TC)",
    "damage": "5",
    "startup": "16~17ad cs6~",
    "block": "-9~-8",
    "hit": "+2~+3",
    "counter": "+2~+3",
    "note": ""
  },
  {
    "input": "d/b+4, 3",
    "hit_level": "l (TC), m",
    "damage": "5,21",
    "startup": "16~17 6~",
    "block": "-17~-16",
    "hit": "Launch",
    "counter": "Launch",
    "note": ""
  },
  {
    "input": "d/b+1+2",
    "hit_level": "!",
    "damage": "50",
    "startup": "65",
    "block": "CS",
    "hit": "CS",
    "counter": "CS",
    "note": ""
  },
  {
    "input": "d/b+3+4",
    "hit_level": "m?",
    "damage": "21",
    "startup": "19~20",
    "block": "-17~-16",
    "hit": "Launch",
    "counter": "Launch",
    "note": ""
  },
  {
    "input": "b+1",
    "hit_level": "h",
    "damage": "10",
    "startup": "12~13",
    "block": "-7~-6",
    "hit": "+4~+5",
    "counter": "+4~+5",
    "note": ""
  },
  {
    "input": "b+1, 4",
    "hit_level": "h, m",
    "damage": "10,22",
    "startup": "12~13",
    "block": "-14",
    "hit": "+9",
    "counter": "CS",
    "note": ""
  },
  {
    "input": "b+2",
    "hit_level": "h",
    "damage": "12",
    "startup": "12",
    "block": "-14",
    "hit": "-3",
    "counter": "-3",
    "note": "Homing"
  },
  {
    "input": "b+2, 2",
    "hit_level": "h, h",
    "damage": "12,16",
    "startup": "12",
    "block": "-6~-5",
    "hit": "+5~+6",
    "counter": "+5~+6",
    "note": ""
  },
  {
    "input": "b+2, 2, 2",
    "hit_level": "h, h, h",
    "damage": "12,14,20",
    "startup": "12",
    "block": "-9~-8",
    "hit": "+9~+10kg",
    "counter": "KND",
    "note": ""
  },
  {
    "input": "b+2, 2, 2, u or D (Cancel)",
    "hit_level": "h, h, (Special)",
    "damage": "12,14",
    "startup": "12",
    "block": "-10~-9",
    "hit": "+1~+2",
    "counter": "+1~+2",
    "note": ""
  },
  {
    "input": "b+3",
    "hit_level": "m",
    "damage": "10",
    "startup": "18",
    "block": "-6",
    "hit": "+6s",
    "counter": "+6s",
    "note": ""
  },
  {
    "input": "b+3, 4",
    "hit_level": "m, h",
    "damage": "10,17",
    "startup": "18",
    "block": "-8~-7",
    "hit": "KND",
    "counter": "CS",
    "note": ""
  },
  {
    "input": "b+4",
    "hit_level": "h",
    "damage": "15",
    "startup": "14",
    "block": "-7",
    "hit": "+11(SH)",
    "counter": "+18",
    "note": ""
  },
  {
    "input": "b+1+2",
    "hit_level": "m, m",
    "damage": "6,26",
    "startup": "18,26",
    "block": "-7",
    "hit": "CS",
    "counter": "CS",
    "note": ""
  },
  {
    "input": "b+1+4",
    "hit_level": "mm",
    "damage": "4,14",
    "startup": "16,31~32",
    "block": "-15~-14",
    "hit": "Launch",
    "counter": "Launch",
    "note": ""
  },
  {
    "input": "u/b+1",
    "hit_level": "m",
    "damage": "15",
    "startup": "20~21",
    "block": "-16",
    "hit": "CS",
    "counter": "CS",
    "note": ""
  },
  {
    "input": "u/f+1",
    "hit_level": "m (TJ)",
    "damage": "20",
    "startup": "26s js10~",
    "block": "-5",
    "hit": "KND",
    "counter": "KND",
    "note": ""
  },
  {
    "input": "u/f+2",
    "hit_level": "m",
    "damage": "10",
    "startup": "18",
    "block": "-10",
    "hit": "+1",
    "counter": "+1",
    "note": ""
  },
  {
    "input": "u/f+2, 1",
    "hit_level": "m, m",
    "damage": "10,10",
    "startup": "18",
    "block": "-13",
    "hit": "BU",
    "counter": "BU",
    "note": ""
  },
  {
    "input": "u/b+3",
    "hit_level": "m (TJ)",
    "damage": "15",
    "startup": "14 js6~",
    "block": "-15",
    "hit": "-4",
    "counter": "-4",
    "note": ""
  },
  {
    "input": "u+3",
    "hit_level": "m (TJ)",
    "damage": "20",
    "startup": "14 js6~",
    "block": "-15",
    "hit": "KND",
    "counter": "KND",
    "note": ""
  },
  {
    "input": "u/f+3",
    "hit_level": "m (TJ)",
    "damage": "20",
    "startup": "14 js6~",
    "block": "-10",
    "hit": "KND",
    "counter": "KND",
    "note": ""
  },
  {
    "input": "u/f+4",
    "hit_level": "h (TJ)",
    "damage": "23",
    "startup": "18 js9~",
    "block": "-9",
    "hit": "-1",
    "counter": "-1",
    "note": ""
  },
  {
    "input": "u/f+4, 3",
    "hit_level": "h (TJ), l",
    "damage": "23,10",
    "startup": "js9~34 cs35~36",
    "block": "-19",
    "hit": "-8",
    "counter": "-8",
    "note": ""
  },
  {
    "input": "u/f+4, 3, 4",
    "hit_level": "h (TJ), l, h",
    "damage": "23,10,14",
    "startup": "9~34 35~36",
    "block": "-6",
    "hit": "+5",
    "counter": "+",
    "note": ""
  },
  {
    "input": "u/f+4, 3, 4, d or u (Cancel)",
    "hit_level": "h (TJ), l, (Special)",
    "damage": "23,10",
    "startup": "js9~34 cs35~36",
    "block": "-5",
    "hit": "+6",
    "counter": "+6",
    "note": ""
  },
  {
    "input": "u/b+4",
    "hit_level": "m (TJ)",
    "damage": "21",
    "startup": "23~28 js7~",
    "block": "-7~-2",
    "hit": "+3~+8s",
    "counter": "KND",
    "note": ""
  },
  {
    "input": "u+4",
    "hit_level": "m (TJ)",
    "damage": "21",
    "startup": "23~28 js7~",
    "block": "0~+5",
    "hit": "+5~+10s",
    "counter": "KND",
    "note": ""
  },
  {
    "input": "U/F+4",
    "hit_level": "m (TJ)",
    "damage": "21",
    "startup": "23~28 js9~",
    "block": "0~+5",
    "hit": "+5~+10s",
    "counter": "KND",
    "note": ""
  },
  {
    "input": "u/f, n, D+3",
    "hit_level": "(Special), l (TC)",
    "damage": "15",
    "startup": "43 js9~ cs34~",
    "block": "-17",
    "hit": "-6",
    "counter": "-6",
    "note": ""
  },
  {
    "input": "u/f, n, D+3, 2",
    "hit_level": "l (TC), m",
    "damage": "15,10",
    "startup": "43 9~ 34~",
    "block": "-13~-11",
    "hit": "Launch",
    "counter": "Launch",
    "note": ""
  },
  {
    "input": "u/f, n, D+3, 4",
    "hit_level": "l (TC), h",
    "damage": "15,18",
    "startup": "43 9~ 34~",
    "block": "-6",
    "hit": "+5",
    "counter": "Launch",
    "note": ""
  },
  {
    "input": "u/f, n, D+3, 4, 3",
    "hit_level": "l (TC), h, m",
    "damage": "15,18,20",
    "startup": "43 9~ 34~",
    "block": "+2~+3s",
    "hit": "+5~+6s",
    "counter": "KND",
    "note": ""
  },
  {
    "input": "f, F+2",
    "hit_level": "h",
    "damage": "20",
    "startup": "14(15~)",
    "block": "-9",
    "hit": "KND",
    "counter": "KND",
    "note": ""
  },
  {
    "input": "f, F+3",
    "hit_level": "m",
    "damage": "24",
    "startup": "15(16~)",
    "block": "-14",
    "hit": "+8",
    "counter": "CS",
    "note": ""
  },
  {
    "input": "f, F+4 (Close)",
    "hit_level": "m (TJ)",
    "damage": "30",
    "startup": "28ad (29~) js5~",
    "block": "+11",
    "hit": "+9s",
    "counter": "KND",
    "note": ""
  },
  {
    "input": "f, F+4",
    "hit_level": "m (TJ)",
    "damage": "20",
    "startup": "28~32ad (29~) js5~",
    "block": "-10~-6",
    "hit": "+9~+13s",
    "counter": "KND",
    "note": ""
  },
  {
    "input": "f, F+4, Tech (Close)",
    "hit_level": "m (TJ), (Special)",
    "damage": "30",
    "startup": "28a(29~) js5~",
    "block": "+4",
    "hit": "+2s",
    "counter": "KND",
    "note": ""
  },
  {
    "input": "f, F+4, Tech",
    "hit_level": "m (TJ), (Special)",
    "damage": "20",
    "startup": "28~32a (29~) js5~",
    "block": "-17~-13",
    "hit": "+2~+6s",
    "counter": "KND",
    "note": ""
  },
  {
    "input": "f, F+1+2",
    "hit_level": "m",
    "damage": "26",
    "startup": "22~23 (23~)",
    "block": "-5",
    "hit": "KND",
    "counter": "KND",
    "note": "wb!"
  },
  {
    "input": "f, F+1+2* (Long hold)",
    "hit_level": "m",
    "damage": "32",
    "startup": "33~34 (34~)",
    "block": "+11~+12g (+16~+17g wc) ",
    "hit": "KND",
    "counter": "KND",
    "note": "Wall bounce, Wall crush"
  },
  {
    "input": "d, D/F+4",
    "hit_level": "l (TC)",
    "damage": "20",
    "startup": "24~28s (26~) cs1~",
    "block": "-37",
    "hit": "KND",
    "counter": "JG",
    "note": ""
  },
  {
    "input": "FC+d/f+4",
    "hit_level": "l (TC)",
    "damage": "20",
    "startup": "20~24s cs1~",
    "block": "-37",
    "hit": "KND",
    "counter": "JG",
    "note": ""
  },
  {
    "input": "qcb",
    "hit_level": "(Special)",
    "damage": "",
    "startup": "(s)",
    "block": "",
    "hit": "",
    "counter": "",
    "note": ""
  },
  {
    "input": "QCB+4",
    "hit_level": "m",
    "damage": "20",
    "startup": "19~20 (21~) cs1~3",
    "block": "-15~-14",
    "hit": "Launch",
    "counter": "Launch",
    "note": ""
  },
  {
    "input": "d/b, qcf, n, d/b+2+3",
    "hit_level": "h!",
    "damage": "0",
    "startup": "35~52 (41?~)",
    "block": "+33~+50 (SH)",
    "hit": "+33~+50 (SH)",
    "counter": "+33~+50 (SH)",
    "note": ""
  },
  {
    "input": "u/f+3+4",
    "hit_level": "m (TJ)",
    "damage": "20(,18)",
    "startup": "23ad(26~) js3~",
    "block": "-23",
    "hit": "Throw(KND)",
    "counter": "Throw(KND)",
    "note": ""
  },
  {
    "input": "u/f+3+4(Crouching or far)",
    "hit_level": "m (TJ)",
    "damage": "20",
    "startup": "24~30ad (27~) js1~",
    "block": "-22~-16",
    "hit": "KND",
    "counter": "KND",
    "note": ""
  },
  {
    "input": "WR+3 or f, f, f+3",
    "hit_level": "m (TJ)",
    "damage": "13",
    "startup": "20 js4~",
    "block": "-13",
    "hit": "-2",
    "counter": "-2",
    "note": ""
  },
  {
    "input": "WR+3 or f, f, f+3, 4",
    "hit_level": "m (TJ), m",
    "damage": "13,23",
    "startup": "20 js4~",
    "block": "-13",
    "hit": "KND",
    "counter": "KND",
    "note": ""
  },
  {
    "input": "f, f, f+1+2",
    "hit_level": "m (TJ)",
    "damage": "30",
    "startup": "20~21a (23~) js5~17",
    "block": "+4~+5",
    "hit": "KND",
    "counter": "KND",
    "note": ""
  },
  {
    "input": "WS+1",
    "hit_level": "m",
    "damage": "17",
    "startup": "13~14",
    "block": "-6~-5",
    "hit": "+5~+6",
    "counter": "+5~+6",
    "note": ""
  },
  {
    "input": "WS+1, 4",
    "hit_level": "m, m",
    "damage": "14,20",
    "startup": "13~14",
    "block": "-3~-2s",
    "hit": "KND",
    "counter": "KND",
    "note": ""
  },
  {
    "input": "WS+1, 1+2",
    "hit_level": "m, hh",
    "damage": "17,3,15",
    "startup": "13~14",
    "block": "-7~-6",
    "hit": "KND",
    "counter": "KND",
    "note": ""
  },
  {
    "input": "WS+2",
    "hit_level": "m",
    "damage": "15",
    "startup": "15~16",
    "block": "-13~-12",
    "hit": "Launch",
    "counter": "Launch",
    "note": ""
  },
  {
    "input": "WS+3",
    "hit_level": "m",
    "damage": "15",
    "startup": "13",
    "block": "-13",
    "hit": "+2",
    "counter": "+2",
    "note": ""
  },
  {
    "input": "WS+4",
    "hit_level": "m",
    "damage": "15",
    "startup": "11~12",
    "block": "-4~-3",
    "hit": "+7~+8",
    "counter": "+7~+8",
    "note": ""
  },
  {
    "input": "WS+4, 3",
    "hit_level": "m, h",
    "damage": "15,24",
    "startup": "11~12",
    "block": "-6",
    "hit": "KND",
    "counter": "CS",
    "note": "Tail spin"
  },
  {
    "input": "WS+b+1",
    "hit_level": "m",
    "damage": "13",
    "startup": "14~15",
    "block": "-5~-4",
    "hit": "+6~+7",
    "counter": "JG",
    "note": ""
  },
  {
    "input": "FC+2",
    "hit_level": "Sm (TC)",
    "damage": "8",
    "startup": "11s cs1~",
    "block": "-4",
    "hit": "+7",
    "counter": "+7",
    "note": ""
  },
  {
    "input": "FC+2, 4",
    "hit_level": "Sm (TC), m",
    "damage": "8,10",
    "startup": "11 1~",
    "block": "-10~-8",
    "hit": "+1~+3",
    "counter": "+1~+3",
    "note": ""
  },
  {
    "input": "SS+1",
    "hit_level": "m",
    "damage": "15",
    "startup": "14~15 (23~)",
    "block": "-10~-9",
    "hit": "+3~+4",
    "counter": "+3~+4",
    "note": ""
  },
  {
    "input": "SS+1, F",
    "hit_level": "m, (Special)",
    "damage": "15",
    "startup": "14~15 (23~)",
    "block": "+10~+11",
    "hit": "+24~+25g",
    "counter": "+24~+25g",
    "note": ""
  },
  {
    "input": "SS+1, B",
    "hit_level": "m, (Special)",
    "damage": "15",
    "startup": "14~15 (23~)",
    "block": "+10~+11",
    "hit": "+23~+24g",
    "counter": "+23~+24g",
    "note": ""
  },
  {
    "input": "SS+1, 2",
    "hit_level": "m, m",
    "damage": "15,15",
    "startup": "14~15 (23~)",
    "block": "-6~-4",
    "hit": "0~+2",
    "counter": "0~+2",
    "note": ""
  },
  {
    "input": "SS+2",
    "hit_level": "m",
    "damage": "15",
    "startup": "13~14 (22~)",
    "block": "-14~-13",
    "hit": "Launch",
    "counter": "Launch",
    "note": ""
  },
  {
    "input": "SS+4",
    "hit_level": "l (TC)",
    "damage": "17",
    "startup": "20(29~) cs6~",
    "block": "-14",
    "hit": "+6s",
    "counter": "JG",
    "note": ""
  },
  {
    "input": "SS+1+2",
    "hit_level": "m",
    "damage": "22",
    "startup": "19(28~)",
    "block": "-11",
    "hit": "KND",
    "counter": "KND",
    "note": ""
  },
  {
    "input": "Opponent Down d+3+4",
    "hit_level": "l(On grounded opponent)",
    "damage": "16 (20)",
    "startup": "17~18",
    "block": "-17~-16",
    "hit": "-8~-7s",
    "counter": "-8~-7s",
    "note": ""
  },
  {
    "input": "qcf",
    "hit_level": "(Special)",
    "damage": "",
    "startup": "17~18",
    "block": "",
    "hit": "",
    "counter": "",
    "note": ""
  },
  {
    "input": "qcf+1+2",
    "hit_level": "h(Throw)",
    "damage": "15",
    "startup": "11",
    "block": "",
    "hit": "Throw(0)",
    "counter": "",
    "note": ""
  },
  {
    "input": "qcf+3+4",
    "hit_level": "h(Throw)",
    "damage": "15",
    "startup": "11",
    "block": "",
    "hit": "Throw(KND)",
    "counter": "",
    "note": ""
  },
  {
    "input": "qcf+1",
    "hit_level": "h",
    "damage": "21",
    "startup": "13~14 (15~) cs1~3",
    "block": "+1~+2",
    "hit": "+3~+4",
    "counter": "Launch",
    "note": ""
  },
  {
    "input": "qcf+2",
    "hit_level": "m?",
    "damage": "25",
    "startup": "17~18 (22~)",
    "block": "-8~-7",
    "hit": "KND",
    "counter": "KND",
    "note": ""
  },
  {
    "input": "qcf+3",
    "hit_level": "l (TC)",
    "damage": "17",
    "startup": "19~28 (21~) cs10~",
    "block": "-20~-11",
    "hit": "0~+9s",
    "counter": "CS",
    "note": ""
  },
  {
    "input": "qcf+4",
    "hit_level": "m",
    "damage": "15",
    "startup": "14(16~)",
    "block": "-8",
    "hit": "+6a",
    "counter": "+6a",
    "note": ""
  },
  {
    "input": "qcf+4, 2",
    "hit_level": "m, h",
    "damage": "15,10",
    "startup": "14(16~)",
    "block": "-9",
    "hit": "-3(Launch)",
    "counter": "-3(Launch)",
    "note": ""
  },
  {
    "input": "qcf+4, 2, 3",
    "hit_level": "m, h, h",
    "damage": "15,10,23",
    "startup": "14(16~)",
    "block": "-10",
    "hit": "KND",
    "counter": "KND",
    "note": ""
  },
  {
    "input": "qcf, 1",
    "hit_level": "m",
    "damage": "14",
    "startup": "13~14 (16~)",
    "block": "-6~-5",
    "hit": "+5~+6",
    "counter": "+5~+6",
    "note": ""
  },
  {
    "input": "d, d/f, N",
    "hit_level": "",
    "damage": "",
    "startup": "13~14 (16~)",
    "block": "",
    "hit": "",
    "counter": "",
    "note": ""
  },
  {
    "input": "1",
    "hit_level": "h",
    "damage": "7",
    "startup": "10",
    "block": "+1",
    "hit": "+8",
    "counter": "+8",
    "note": ""
  },
  {
    "input": "2",
    "hit_level": "h",
    "damage": "10",
    "startup": "10",
    "block": "+1",
    "hit": "+7",
    "counter": "+7",
    "note": ""
  },
  {
    "input": "3",
    "hit_level": "h",
    "damage": "14",
    "startup": "14",
    "block": "-16",
    "hit": "-5",
    "counter": "-5",
    "note": ""
  },
  {
    "input": "4",
    "hit_level": "h",
    "damage": "15",
    "startup": "11",
    "block": "-9",
    "hit": "+8",
    "counter": "Launch (JG?)",
    "note": ""
  },
  {
    "input": "f+1",
    "hit_level": "h",
    "damage": "7",
    "startup": "10",
    "block": "+1",
    "hit": "+8",
    "counter": "+8",
    "note": ""
  },
  {
    "input": "f+2",
    "hit_level": "h",
    "damage": "12",
    "startup": "13",
    "block": "-3",
    "hit": "+8",
    "counter": "+8",
    "note": ""
  },
  {
    "input": "f+3",
    "hit_level": "hh",
    "damage": "10,20",
    "startup": "14~15, 26~27",
    "block": "+6~+7 (-24s)",
    "hit": "KND",
    "counter": "CS",
    "note": ""
  },
  {
    "input": "f+4",
    "hit_level": "h",
    "damage": "14",
    "startup": "16",
    "block": "-12",
    "hit": "-3",
    "counter": "-1",
    "note": ""
  },
  {
    "input": "d/f+1",
    "hit_level": "m",
    "damage": "13",
    "startup": "13~12",
    "block": "-1~0",
    "hit": "+5~+6",
    "counter": "+5~+6",
    "note": ""
  },
  {
    "input": "d/f+2",
    "hit_level": "m",
    "damage": "12",
    "startup": "15~16",
    "block": "-7~-6",
    "hit": "Launch (JG?)(+4a)",
    "counter": "Launch (JG?)",
    "note": ""
  },
  {
    "input": "d/f+3",
    "hit_level": "m",
    "damage": "13",
    "startup": "14",
    "block": "-11",
    "hit": "+1",
    "counter": "+1",
    "note": ""
  },
  {
    "input": "d/f+4",
    "hit_level": "m",
    "damage": "15",
    "startup": "12",
    "block": "-4",
    "hit": "+7",
    "counter": "+7",
    "note": ""
  },
  {
    "input": "d/b or d+1",
    "hit_level": "Sm (TC)",
    "damage": "5",
    "startup": "10s cs4~",
    "block": "-5",
    "hit": "+6",
    "counter": "+6",
    "note": ""
  },
  {
    "input": "d+2",
    "hit_level": "l (TC)",
    "damage": "13",
    "startup": "20s cs6~",
    "block": "-12",
    "hit": "0",
    "counter": "+5",
    "note": ""
  },
  {
    "input": "d+3",
    "hit_level": "l (TC)",
    "damage": "12",
    "startup": "16s cs4~",
    "block": "-17",
    "hit": "-3",
    "counter": "-3",
    "note": ""
  },
  {
    "input": "d+4",
    "hit_level": "l (TC)",
    "damage": "7",
    "startup": "12s cs4~",
    "block": "-13",
    "hit": "-2",
    "counter": "-2",
    "note": ""
  },
  {
    "input": "d/b or d+1 ",
    "hit_level": "Sm (TC)",
    "damage": "5",
    "startup": "10s cs4~",
    "block": "-5",
    "hit": "+6",
    "counter": "+6",
    "note": ""
  },
  {
    "input": "d/b+2",
    "hit_level": "m",
    "damage": "20",
    "startup": "24~25",
    "block": "-5~-4",
    "hit": "KND",
    "counter": "KND",
    "note": "Tail spin, Homing"
  },
  {
    "input": "d/b+3",
    "hit_level": "l",
    "damage": "17",
    "startup": "20",
    "block": "-13",
    "hit": "+4s",
    "counter": "KND",
    "note": ""
  },
  {
    "input": "d/b+4",
    "hit_level": "l (TC)",
    "damage": "5",
    "startup": "16~17ad cs6~",
    "block": "-9~-8",
    "hit": "+2~+3",
    "counter": "+2~+3",
    "note": ""
  },
  {
    "input": "b+1",
    "hit_level": "h",
    "damage": "10",
    "startup": "12~13",
    "block": "-7~-6",
    "hit": "+4~+5",
    "counter": "+4~+5",
    "note": ""
  },
  {
    "input": "b+2",
    "hit_level": "h",
    "damage": "12",
    "startup": "12",
    "block": "-14",
    "hit": "-3",
    "counter": "-3",
    "note": "Homing"
  },
  {
    "input": "b+3",
    "hit_level": "m",
    "damage": "10",
    "startup": "18",
    "block": "-6",
    "hit": "+6s",
    "counter": "+6s",
    "note": ""
  },
  {
    "input": "b+4",
    "hit_level": "h",
    "damage": "15",
    "startup": "14",
    "block": "-7",
    "hit": "+11(SH)",
    "counter": "+18",
    "note": ""
  },
  {
    "input": "u/b+1",
    "hit_level": "m",
    "damage": "15",
    "startup": "20~21",
    "block": "-16",
    "hit": "CS",
    "counter": "CS",
    "note": ""
  },
  {
    "input": "u+1",
    "hit_level": "m (TJ)",
    "damage": "12",
    "startup": "18 js9~",
    "block": "-8",
    "hit": "+3",
    "counter": "+3",
    "note": ""
  },
  {
    "input": "u/f+1",
    "hit_level": "m (TJ)",
    "damage": "20",
    "startup": "26s js10~",
    "block": "-5",
    "hit": "KND",
    "counter": "KND",
    "note": ""
  },
  {
    "input": "u/b or u+2",
    "hit_level": "h",
    "damage": "17",
    "startup": "15~16",
    "block": "-12~-11",
    "hit": "+9~+10g",
    "counter": "+9~+10g",
    "note": ""
  },
  {
    "input": "u/f+2",
    "hit_level": "m",
    "damage": "10",
    "startup": "18",
    "block": "-10",
    "hit": "+1",
    "counter": "+1",
    "note": ""
  },
  {
    "input": "u/b+3",
    "hit_level": "m (TJ)",
    "damage": "15",
    "startup": "14 js6~",
    "block": "-15",
    "hit": "-4",
    "counter": "-4",
    "note": ""
  },
  {
    "input": "u+3",
    "hit_level": "m (TJ)",
    "damage": "20",
    "startup": "14 js6~",
    "block": "-15",
    "hit": "KND",
    "counter": "KND",
    "note": ""
  },
  {
    "input": "u/f+3",
    "hit_level": "m (TJ)",
    "damage": "20",
    "startup": "14 js6~",
    "block": "-10",
    "hit": "KND",
    "counter": "KND",
    "note": ""
  },
  {
    "input": "u/b+4",
    "hit_level": "m (TJ)",
    "damage": "21",
    "startup": "23~28 js7~",
    "block": "-7~-2",
    "hit": "+3~+8s",
    "counter": "KND",
    "note": ""
  },
  {
    "input": "u+4",
    "hit_level": "m (TJ)",
    "damage": "21",
    "startup": "23~28 js7~",
    "block": "0~+5",
    "hit": "+5~+10s",
    "counter": "KND",
    "note": ""
  },
  {
    "input": "U/F+4",
    "hit_level": "m (TJ)",
    "damage": "21",
    "startup": "23~28 js9~",
    "block": "0~+5",
    "hit": "+5~+10s",
    "counter": "KND",
    "note": ""
  },
  {
    "input": "u/f+4",
    "hit_level": "h (TJ)",
    "damage": "23",
    "startup": "18 js9~",
    "block": "-9",
    "hit": "-1",
    "counter": "-1",
    "note": ""
  },
  {
    "input": "WS+1",
    "hit_level": "m",
    "damage": "14",
    "startup": "13~14",
    "block": "-6~-5",
    "hit": "+5~+6",
    "counter": "+5~+6",
    "note": ""
  },
  {
    "input": "WS+2",
    "hit_level": "m",
    "damage": "15",
    "startup": "15~16",
    "block": "-13~-12",
    "hit": "Launch (JG?)",
    "counter": "Launch (JG?)",
    "note": ""
  },
  {
    "input": "WS+3",
    "hit_level": "m",
    "damage": "15",
    "startup": "18",
    "block": "-13",
    "hit": "+2",
    "counter": "+2",
    "note": ""
  },
  {
    "input": "WS+4",
    "hit_level": "m",
    "damage": "15",
    "startup": "11~12",
    "block": "-4~-3",
    "hit": "+7~+8",
    "counter": "+7~+8",
    "note": ""
  },
  {
    "input": "WS+3+4",
    "hit_level": "h",
    "damage": "25",
    "startup": "16",
    "block": "-16",
    "hit": "KND",
    "counter": "KND",
    "note": ""
  },
  {
    "input": "FC+1",
    "hit_level": "Sm (TC)",
    "damage": "5",
    "startup": "10s cs1~",
    "block": "-5",
    "hit": "+6",
    "counter": "+6",
    "note": ""
  },
  {
    "input": "FC+2",
    "hit_level": "Sm (TC)",
    "damage": "8",
    "startup": "11s cs1~",
    "block": "-4",
    "hit": "+7",
    "counter": "+7",
    "note": ""
  },
  {
    "input": "FC+3",
    "hit_level": "l (TC)",
    "damage": "12",
    "startup": "16s cs1~",
    "block": "-17",
    "hit": "-3",
    "counter": "-3",
    "note": ""
  },
  {
    "input": "FC+d/b or d+4",
    "hit_level": "l (TC)",
    "damage": "10",
    "startup": "12s cs1~",
    "block": "-15",
    "hit": "-4",
    "counter": "-4",
    "note": ""
  },
  {
    "input": "SS+1",
    "hit_level": "m",
    "damage": "15",
    "startup": "14~15 (23~)",
    "block": "-10~-9",
    "hit": "+3~+4",
    "counter": "+3~+4",
    "note": ""
  },
  {
    "input": "SS+2",
    "hit_level": "m",
    "damage": "15",
    "startup": "13~14 (22~)",
    "block": "-14~-13",
    "hit": "Launch (JG?)",
    "counter": "Launch (JG?)",
    "note": ""
  },
  {
    "input": "SS+3",
    "hit_level": "h",
    "damage": "14",
    "startup": "14(15~)",
    "block": "-16",
    "hit": "-5",
    "counter": "-5",
    "note": ""
  },
  {
    "input": "SS+4",
    "hit_level": "l (TC)",
    "damage": "17",
    "startup": "20(29~) cs6~",
    "block": "-14",
    "hit": "+6s",
    "counter": "YKU",
    "note": ""
  },
  {
    "input": "BT 1 or 2",
    "hit_level": "h",
    "damage": "15",
    "startup": "8",
    "block": "-8",
    "hit": "+3",
    "counter": "+3",
    "note": ""
  },
  {
    "input": "BT 3 or 4",
    "hit_level": "h",
    "damage": "25",
    "startup": "10",
    "block": "-8",
    "hit": "KND",
    "counter": "KND",
    "note": ""
  },
  {
    "input": "BT d+1 or 2",
    "hit_level": "Sm",
    "damage": "10",
    "startup": "10s cs1~",
    "block": "-2",
    "hit": "+9",
    "counter": "+9",
    "note": ""
  },
  {
    "input": "BT d+3 or 4",
    "hit_level": "l",
    "damage": "12",
    "startup": "10s cs1~",
    "block": "-11",
    "hit": "+3",
    "counter": "+3",
    "note": ""
  }
]
