[
  {
    "name": "Heat Burst",
    "input": "2+3",
    "hit_level": "m",
    "damage": "12",
    "startup": "i16",
    "block": "+1",
    "hit": "+2c",
    "counter": "",
    "note": "\npc8~\nHeat Burst\nCancel move with b,b\n",
    "alternateInputs": ["2+3"]
  },
  {
    "name": "Yinglong Mountain Crusher",
    "input": "in heat 2+3",
    "hit_level": "m,m",
    "damage": "22,26",
    "startup": "i21,24",
    "block": "+12",
    "hit": "+30d (-6)",
    "counter": "",
    "note": "\nHeat Smash\nChip damage on block\nTransitions to STC on block\n",
    "alternateInputs": ["in heat 2+3"]
  },
  {
    "name": "Jiaolong Sea Splitter",
    "input": "in heat 3+4",
    "hit_level": "ub(m)",
    "damage": "30",
    "startup": "i30~31",
    "block": "+12c g",
    "hit": "+19d",
    "counter": "",
    "note": "\nPartially consumes remaining Heat\nCreates an unblockable shockwave along the ground that is +10g on hit and forces the opponent to crouch. The shockwave comes out even if the kick itself whiffs, or is parried by certain parries like Jin's or Reina's. It can be absorbed by a Power Crush.\n",
    "alternateInputs": ["in heat 3+4"]
  },
  {
    "name": "Tiger's Claw",
    "input": "f+1+2",
    "hit_level": "h",
    "damage": "25",
    "startup": "i19~20",
    "block": "-9",
    "hit": "+19d",
    "counter": "",
    "note": "\npc\n\nHeat Engager\n\n\nHeat Dash +5, +35d\n\n\nBalcony Break\n",
    "alternateInputs": ["f+1+2"]
  },
  {
    "name": "Iron Fortress",
    "input": "b+1+2",
    "hit_level": "m",
    "damage": "31",
    "startup": "i13~14",
    "block": "-19",
    "hit": "+18a (+13)",
    "counter": "",
    "note": "\n\nHeat Engager\n\n\nHeat Dash +5, +43d (+35)\n\n\nBalcony Break\n",
    "alternateInputs": ["b+1+2"]
  },
  {
    "name": "Exploding Dagger",
    "input": "f,F+2",
    "hit_level": "m",
    "damage": "25",
    "startup": "i18~19",
    "block": "-9",
    "hit": "+16a (+7)",
    "counter": "",
    "note": "\n\nHeat Engager\n\n\nHeat Dash +5, +36a (+26)\n\n\nBalcony Break\n",
    "alternateInputs": ["f,F+2"]
  },
  {
    "name": "Fei He Zhang",
    "input": "KNP 2",
    "hit_level": "h",
    "damage": "20",
    "startup": "i14",
    "block": "-9",
    "hit": "+17",
    "counter": "",
    "note": "\n\nHeat Engager\n\n\nBalcony Break\n",
    "alternateInputs": ["KNP 2"]
  },
  {
    "name": "Slashing Tiger",
    "input": "BT 2",
    "hit_level": "m",
    "damage": "23",
    "startup": "i19~21",
    "block": "-13",
    "hit": "+17",
    "counter": "",
    "note": "\npc\n\nHeat Engager\n\nAbsorb an attack to power up and deal more damage on block\n",
    "alternateInputs": ["BT 2"]
  },
  {
    "name": "Essence of Iron Palm",
    "input": "in heat b+1",
    "hit_level": "h",
    "damage": "20",
    "startup": "i10~11",
    "block": "-8",
    "hit": "+36d (+28)",
    "counter": "",
    "note": "\n\nBalcony Break\nPartially uses remaining Heat Time\n",
    "alternateInputs": ["in heat b+1"]
  },
  {
    "name": "Essence of Nian Zhang Mie Ba",
    "input": "in heat f,F+1+2*",
    "hit_level": "m",
    "damage": "30",
    "startup": "i39",
    "block": "+11",
    "hit": "+22a (+12)",
    "counter": "",
    "note": "\n\nBalcony Break\n\nGuard Break +11\nPartially uses remaining Heat Time\n",
    "alternateInputs": ["in heat f,F+1+2*"]
  },
  {
    "name": "Left Jab",
    "input": "1",
    "hit_level": "h",
    "damage": "5",
    "startup": "i10",
    "block": "+1",
    "hit": "+8",
    "counter": "",
    "note": "",
    "alternateInputs": ["1"]
  },
  {
    "name": "Jab Spear Fist",
    "input": "1,1",
    "hit_level": "h,m",
    "damage": "5,21",
    "startup": "i25~26",
    "block": "-11",
    "hit": "+2",
    "counter": "+61a",
    "note": "\nMove can be delayed",
    "alternateInputs": ["1,1"]
  },
  {
    "name": "Shun Lian Quan",
    "input": "1,2",
    "hit_level": "h,h",
    "damage": "5,9",
    "startup": "i10",
    "block": "-3",
    "hit": "+8",
    "counter": "",
    "note": "\nJail from 1st attack\nMove can be delayed",
    "alternateInputs": ["1,2"]
  },
  {
    "name": "Firestorm",
    "input": "1,2,2",
    "hit_level": "h,h,h",
    "damage": "5,9,12",
    "startup": "i17",
    "block": "-13",
    "hit": "+3",
    "counter": "",
    "note": "\nCombo from 1st hit\nTransition to -11 +5 BT with B",
    "alternateInputs": ["1,2,2"]
  },
  {
    "name": "Jab Roundhouse Combo",
    "input": "1,3",
    "hit_level": "h,h",
    "damage": "5,19",
    "startup": "i16~17",
    "block": "-5",
    "hit": "+8",
    "counter": "",
    "note": "\nCombo from 1st hit",
    "alternateInputs": ["1,3"]
  },
  {
    "name": "Right Jab",
    "input": "2",
    "hit_level": "h",
    "damage": "8",
    "startup": "i10",
    "block": "-3",
    "hit": "+5",
    "counter": "",
    "note": "",
    "alternateInputs": ["2"]
  },
  {
    "name": "",
    "input": "2,4",
    "hit_level": "h,m",
    "damage": "8,15",
    "startup": "i17",
    "block": "-12",
    "hit": "-1",
    "counter": "",
    "note": "\nJail from 1st attack\n",
    "alternateInputs": ["2,4"]
  },
  {
    "name": "San Liang Heng",
    "input": "2,4,1",
    "hit_level": "h,m,m",
    "damage": "8,15,25",
    "startup": "i24",
    "block": "-12",
    "hit": "+24d (+14)",
    "counter": "",
    "note": "\nBalcony Break\nCombo from 2nd CH\nMove can be delayed\nCancel to -13 -2 BT with B",
    "alternateInputs": ["2,4,1"]
  },
  {
    "name": "",
    "input": "3",
    "hit_level": "h",
    "damage": "15",
    "startup": "i16",
    "block": "-11",
    "hit": "0",
    "counter": "",
    "note": "",
    "alternateInputs": ["3"]
  },
  {
    "name": "",
    "input": "3,3",
    "hit_level": "h,h",
    "damage": "15,18",
    "startup": "i17",
    "block": "-9",
    "hit": "+2",
    "counter": "",
    "note": "\nCombo from 1st hit\nJail from 1st attack\nMove can be delayed",
    "alternateInputs": ["3,3"]
  },
  {
    "name": "Peacock Sweep",
    "input": "3,3,4",
    "hit_level": "h,h,l",
    "damage": "15,18,23",
    "startup": "i25~26",
    "block": "-12",
    "hit": "+17d",
    "counter": "",
    "note": "\nCombo from 2nd CH\nMove can be delayed\nCancel to -13 -2 BT with B",
    "alternateInputs": ["3,3,4"]
  },
  {
    "name": "Peacock Strike",
    "input": "3,1+2",
    "hit_level": "h,m",
    "damage": "15,30",
    "startup": "i28~29",
    "block": "-12",
    "hit": "+22d (+17)",
    "counter": "",
    "note": "\nBalcony Break\nCombo from 1st CH\nCan be charged to power up:\nAt full charge +7 on block 14 chip damage ",
    "alternateInputs": ["3,1+2"]
  },
  {
    "name": "",
    "input": "3~4",
    "hit_level": "m",
    "damage": "27",
    "startup": "i34~36",
    "block": "-5",
    "hit": "+19d",
    "counter": "",
    "note": "\njs\nCancel to -7~-2 -+19~+24 BT with B",
    "alternateInputs": ["3~4"]
  },
  {
    "name": "Leaping Whirlwind Combo",
    "input": "3~4,3",
    "hit_level": "m,L",
    "damage": "27,11",
    "startup": "i18~20",
    "block": "-26",
    "hit": "+19d (+12)",
    "counter": "",
    "note": "\nCombo from 1st hit",
    "alternateInputs": ["3~4,3"]
  },
  {
    "name": "Jiaolong Sea Splitter",
    "input": "in heat 3+4",
    "hit_level": "ub(m)",
    "damage": "30",
    "startup": "i30~31",
    "block": "+12c g",
    "hit": "+19d",
    "counter": "",
    "note": "\nPartially consumes remaining Heat\nCreates an unblockable shockwave along the ground that is +10g on hit and forces the opponent to crouch. The shockwave comes out even if the kick itself whiffs, or is parried by certain parries like Jin's or Reina's. It can be absorbed by a Power Crush.\n",
    "alternateInputs": ["in heat 3+4"]
  },
  {
    "name": "Headspring",
    "input": "4~3",
    "hit_level": "M",
    "damage": "25",
    "startup": "i28~i34",
    "block": "-7",
    "hit": "+1c",
    "counter": "+16a",
    "note": "\njs",
    "alternateInputs": ["4~3"]
  },
  {
    "name": "Iron Shield",
    "input": "1+2",
    "hit_level": "m",
    "damage": "20",
    "startup": "i21~22",
    "block": "-13",
    "hit": "+8",
    "counter": "",
    "note": "\npsPunch sabaki",
    "alternateInputs": ["1+2"]
  },
  {
    "name": "",
    "input": "f+2",
    "hit_level": "m",
    "damage": "10",
    "startup": "i15",
    "block": "-8",
    "hit": "+3",
    "counter": "",
    "note": "",
    "alternateInputs": ["f+2"]
  },
  {
    "name": "",
    "input": "f+2,1",
    "hit_level": "m,m",
    "damage": "10,10",
    "startup": "i19",
    "block": "-8",
    "hit": "+3",
    "counter": "",
    "note": "\nCombo from 1st CH\nMove can be delayed",
    "alternateInputs": ["f+2,1"]
  },
  {
    "name": "Boar's Tusk",
    "input": "f+2,1,2",
    "hit_level": "m,m,m",
    "damage": "10,10,28",
    "startup": "i13~14",
    "block": "-19",
    "hit": "+19d (+14)",
    "counter": "",
    "note": "\n\nBalcony Break\nCombo from 1st CH\nMove can be delayed",
    "alternateInputs": ["f+2,1,2"]
  },
  {
    "name": "",
    "input": "f+3",
    "hit_level": "m",
    "damage": ",10",
    "startup": "i21",
    "block": "-3",
    "hit": "+7",
    "counter": "",
    "note": "",
    "alternateInputs": ["f+3"]
  },
  {
    "name": "Piercing Dragon",
    "input": "f+3,2",
    "hit_level": "m,h",
    "damage": ",10,17",
    "startup": "i21~22",
    "block": "-3",
    "hit": "+8",
    "counter": "+43d (+35)",
    "note": "\nCombo from 1st hit\nMove can be delayed",
    "alternateInputs": ["f+3,2"]
  },
  {
    "name": "Climbing Dragon",
    "input": "f+3,4",
    "hit_level": "m,m",
    "damage": ",10,15",
    "startup": "i23~24",
    "block": "-16",
    "hit": "+33a (+23)",
    "counter": "",
    "note": "\nCombo from 1st hit\n\nTornado ",
    "alternateInputs": ["f+3,4"]
  },
  {
    "name": "",
    "input": "f+4",
    "hit_level": "h",
    "damage": "19",
    "startup": "i18~19",
    "block": "-9",
    "hit": "+52a",
    "counter": "",
    "note": "\nTransition to -5 +56a BT with B",
    "alternateInputs": ["f+4"]
  },
  {
    "name": "Tornado Open Palm",
    "input": "f+4,2",
    "hit_level": "h,m",
    "damage": "19,16",
    "startup": "i24~25",
    "block": "-14",
    "hit": "+70a (+54)",
    "counter": "",
    "note": "\nCombo from 1st hit\n\nTornado\n",
    "alternateInputs": ["f+4,2"]
  },
  {
    "name": "Tornado Stomp",
    "input": "f+4,3",
    "hit_level": "h,m",
    "damage": "19,21",
    "startup": "i22~24",
    "block": "-10",
    "hit": "+26d (-9)",
    "counter": "",
    "note": "\nSpike\nCombo from 1st hit\n",
    "alternateInputs": ["f+4,3"]
  },
  {
    "name": "Tornado Sweep",
    "input": "f+4,4",
    "hit_level": "h,l",
    "damage": "19,11",
    "startup": "i33~33",
    "block": "-31",
    "hit": "+27d",
    "counter": "",
    "note": "\nCombo from 1st hit\n",
    "alternateInputs": ["f+4,4"]
  },
  {
    "name": "Tiger's Claw",
    "input": "f+1+2",
    "hit_level": "h",
    "damage": "25",
    "startup": "i19~20",
    "block": "-9",
    "hit": "+19d",
    "counter": "",
    "note": "\npc\n\nHeat Engager\n\n\nHeat Dash +5, +35d\n\n\nBalcony Break\n",
    "alternateInputs": ["f+1+2"]
  },
  {
    "name": "Stunning Palm",
    "input": "df+1",
    "hit_level": "m",
    "damage": "11",
    "startup": "i14",
    "block": "0",
    "hit": "+6",
    "counter": "+36g",
    "note": "",
    "alternateInputs": ["df+1"]
  },
  {
    "name": "",
    "input": "df+2",
    "hit_level": "m",
    "damage": "15",
    "startup": "i20~21",
    "block": "-8",
    "hit": "",
    "counter": "",
    "note": "",
    "alternateInputs": ["df+2"]
  },
  {
    "name": "God Fist",
    "input": "df+2,2",
    "hit_level": "m,m",
    "damage": "15,21",
    "startup": "i13~14",
    "block": "-6",
    "hit": "+14a (+4)",
    "counter": "",
    "note": "\nBalcony Break\n",
    "alternateInputs": ["df+2,2"]
  },
  {
    "name": "Lift Kick",
    "input": "df+3",
    "hit_level": "m",
    "damage": "21",
    "startup": "i18~19",
    "block": "-7",
    "hit": "+78a (+62)",
    "counter": "",
    "note": "\n\nTornado\n",
    "alternateInputs": ["df+3"]
  },
  {
    "name": "",
    "input": "df+4",
    "hit_level": "m",
    "damage": "13",
    "startup": "i15",
    "block": "-6",
    "hit": "+5",
    "counter": "",
    "note": "",
    "alternateInputs": ["df+4"]
  },
  {
    "name": "",
    "input": "df+4,2",
    "hit_level": "m,m",
    "damage": "13,13",
    "startup": "i20~21",
    "block": "-11",
    "hit": "+1",
    "counter": "",
    "note": "\nCombo from 1st hit\nMove can be delayed\n",
    "alternateInputs": ["df+4,2"]
  },
  {
    "name": "Pau Lau Stinger",
    "input": "df+4,2,1+2",
    "hit_level": "m,m,m",
    "damage": "13,13,21",
    "startup": "i34~35",
    "block": "-19",
    "hit": "+31a (+16)",
    "counter": "",
    "note": "\n\nTornado\nMove can be delayed\n",
    "alternateInputs": ["df+4,2,1+2"]
  },
  {
    "name": "Twin Dragon",
    "input": "df+4,3",
    "hit_level": "m,h",
    "damage": "13,23",
    "startup": "i23~24",
    "block": "-4",
    "hit": "+15g",
    "counter": "",
    "note": "\nBalcony Break\nCombo from 1st hit\nMove can be delayed\n",
    "alternateInputs": ["df+4,3"]
  },
  {
    "name": "Ruinous Halberd",
    "input": "df+3+4",
    "hit_level": "m",
    "damage": "23",
    "startup": "i24 (23~27)",
    "block": "-7",
    "hit": "+22d",
    "counter": "",
    "note": "\nHoming\n",
    "alternateInputs": ["df+3+4"]
  },
  {
    "name": "Heavy Hammer",
    "input": "d+2",
    "hit_level": "l",
    "damage": "16",
    "startup": "i20~21",
    "block": "-12",
    "hit": "-1",
    "counter": "",
    "note": "\ncs",
    "alternateInputs": ["d+2"]
  },
  {
    "name": "",
    "input": "d+4",
    "hit_level": "l",
    "damage": "7",
    "startup": "i14~15",
    "block": "-11",
    "hit": "0",
    "counter": "",
    "note": "",
    "alternateInputs": ["d+4"]
  },
  {
    "name": "Parting Heavens",
    "input": "d+4,1+2",
    "hit_level": "l,m",
    "damage": "7,22",
    "startup": "i26",
    "block": "-10",
    "hit": "+11d (+2)",
    "counter": "",
    "note": "\nBalcony Break\nCombo from 1st CH\n",
    "alternateInputs": ["d+4,1+2"]
  },
  {
    "name": "",
    "input": "d+1+2",
    "hit_level": "m",
    "damage": "15",
    "startup": "i20~21",
    "block": "-9",
    "hit": "+8c",
    "counter": "",
    "note": "",
    "alternateInputs": ["d+1+2"]
  },
  {
    "name": "Mad Windmill",
    "input": "d+1+2,1",
    "hit_level": "m,m",
    "damage": "15,20",
    "startup": "i22~23",
    "block": "-12",
    "hit": "+18a (+11)",
    "counter": "",
    "note": "\n\nTornado\nCombo from 1st CH\nMove can be delayed\n",
    "alternateInputs": ["d+1+2,1"]
  },
  {
    "name": "",
    "input": "db+1",
    "hit_level": "m",
    "damage": "15",
    "startup": "i16",
    "block": "-12",
    "hit": "+4",
    "counter": "",
    "note": "\nTransition to -9 +7 KNP with B\nTransition to -16 +0 STC with F\n",
    "alternateInputs": ["db+1"]
  },
  {
    "name": "Spear of Lu Bu",
    "input": "db+1,2",
    "hit_level": "m,m",
    "damage": "15,18",
    "startup": "i23~24",
    "block": "-11",
    "hit": "+7",
    "counter": "",
    "note": "\nCombo from 1st hit\nMove can be delayed ",
    "alternateInputs": ["db+1,2"]
  },
  {
    "name": "",
    "input": "db+1,2,4",
    "hit_level": "m,m,m",
    "damage": "15,18,30",
    "startup": "i31",
    "block": "-7",
    "hit": "-3d",
    "counter": "",
    "note": "\njs\n\nFloor Break ",
    "alternateInputs": ["db+1,2,4"]
  },
  {
    "name": "Rampaging Lion",
    "input": "db+1,2,4,3+4",
    "hit_level": "m,m,m",
    "damage": "15,18,30",
    "startup": "i39",
    "block": "",
    "hit": "-",
    "counter": "",
    "note": "\njs\nFeng does a kip-up to get off the floor\n",
    "alternateInputs": ["db+1,2,4,3+4"]
  },
  {
    "name": "Spinning Neck Strike",
    "input": "db+1,4",
    "hit_level": "m,h",
    "damage": "15,23",
    "startup": "i24~25",
    "block": "-2",
    "hit": "+24a (+15)",
    "counter": "",
    "note": "\n\nBalcony Break\nCombo from 1st hit\nMove can be delayed\n",
    "alternateInputs": ["db+1,4"]
  },
  {
    "name": "",
    "input": "db+2",
    "hit_level": "l",
    "damage": "10",
    "startup": "i20~21",
    "block": "-11",
    "hit": "0",
    "counter": "",
    "note": "",
    "alternateInputs": ["db+2"]
  },
  {
    "name": "",
    "input": "db+2,2",
    "hit_level": "l,l",
    "damage": "10,10",
    "startup": "i28~30",
    "block": "-17",
    "hit": "+20a",
    "counter": "",
    "note": "\nCombo from 1st CH\nCancel move with B\n",
    "alternateInputs": ["db+2,2"]
  },
  {
    "name": "Hellwinds",
    "input": "db+2,2,2",
    "hit_level": "l,l,m",
    "damage": "10,10,25",
    "startup": "i28~29",
    "block": "-8",
    "hit": "+13d",
    "counter": "",
    "note": "\nSpike\nCombo from 1st CH\n",
    "alternateInputs": ["db+2,2,2"]
  },
  {
    "name": "Piercing Arrow",
    "input": "db+3",
    "hit_level": "l",
    "damage": "14",
    "startup": "i17",
    "block": "-15",
    "hit": "+4",
    "counter": "",
    "note": "\nTransition to throw when CH from front\n",
    "alternateInputs": ["db+3"]
  },
  {
    "name": "Mighty Sweep Kick",
    "input": "db+4",
    "hit_level": "l",
    "damage": "23",
    "startup": "i31 (30~32)",
    "block": "-26",
    "hit": "+76a (+60)",
    "counter": "",
    "note": "\nTornado\nHoming\n",
    "alternateInputs": ["db+4"]
  },
  {
    "name": "",
    "input": "db+1+2",
    "hit_level": "m",
    "damage": "13",
    "startup": "i21~22",
    "block": "-4",
    "hit": "+4",
    "counter": "",
    "note": "",
    "alternateInputs": ["db+1+2"]
  },
  {
    "name": "Dragon Slayer",
    "input": "db+1+2,2",
    "hit_level": "m,l",
    "damage": "13,10",
    "startup": "i29~30",
    "block": "-12",
    "hit": "-1",
    "counter": "",
    "note": "\nCombo from 1st CH\nMove can be delayed\n",
    "alternateInputs": ["db+1+2,2"]
  },
  {
    "name": "Iron Palm",
    "input": "b+1",
    "hit_level": "h",
    "damage": "17",
    "startup": "i10~11",
    "block": "-12",
    "hit": "+1",
    "counter": "+36d (+28)",
    "note": "",
    "alternateInputs": ["b+1"]
  },
  {
    "name": "Essence of Iron Palm",
    "input": "in heat b+1",
    "hit_level": "h",
    "damage": "20",
    "startup": "i10~11",
    "block": "-8",
    "hit": "+36d (+28)",
    "counter": "",
    "note": "\nConsumes Heat\n",
    "alternateInputs": ["in heat b+1"]
  },
  {
    "name": "",
    "input": "b+2",
    "hit_level": "m",
    "damage": "15",
    "startup": "i17",
    "block": "-11",
    "hit": "+0c",
    "counter": "",
    "note": "Floor Break",
    "alternateInputs": ["b+2"]
  },
  {
    "name": "",
    "input": "b+2,3",
    "hit_level": "m,l",
    "damage": "15,10",
    "startup": "i22~24",
    "block": "-11",
    "hit": "0",
    "counter": "",
    "note": "\nCombo from 1st CH\nMove can be delayed\n",
    "alternateInputs": ["b+2,3"]
  },
  {
    "name": "",
    "input": "b+2,3,4",
    "hit_level": "m,l,m",
    "damage": "15,10,13",
    "startup": "i24~25",
    "block": "-12",
    "hit": "+19a (+12)",
    "counter": "",
    "note": "\nCombo from 2nd hit\n",
    "alternateInputs": ["b+2,3,4"]
  },
  {
    "name": "Hungry Tiger",
    "input": "b+2,3,4,2",
    "hit_level": "m,l,m,m",
    "damage": "15,10,13,22",
    "startup": "i24~25",
    "block": "-6",
    "hit": "+4",
    "counter": "",
    "note": "\nCombo from 3rd hit\n\nSpike\n",
    "alternateInputs": ["b+2,3,4,2"]
  },
  {
    "name": "Chin Breaker",
    "input": "b+3",
    "hit_level": "m",
    "damage": "21",
    "startup": "i22~23",
    "block": "+6",
    "hit": "+10d",
    "counter": "+38a",
    "note": "",
    "alternateInputs": ["b+3"]
  },
  {
    "name": "Fish Hook",
    "input": "b+4",
    "hit_level": "m",
    "damage": "10",
    "startup": "i12~13",
    "block": "-9",
    "hit": "+4",
    "counter": "",
    "note": "",
    "alternateInputs": ["b+4"]
  },
  {
    "name": "Iron Fortress",
    "input": "b+1+2",
    "hit_level": "m",
    "damage": "31",
    "startup": "i13~14",
    "block": "-19",
    "hit": "+18a (+13)",
    "counter": "",
    "note": "\n\nHeat Engager\n\n\nHeat Dash +5, +43d (+35)\n\n\nBalcony Break\n",
    "alternateInputs": ["b+1+2"]
  },
  {
    "name": "Throat Gouge",
    "input": "ub+2",
    "hit_level": "m,h",
    "damage": "8,20",
    "startup": "i16,15",
    "block": "-10",
    "hit": "+10g",
    "counter": "",
    "note": "",
    "alternateInputs": ["ub+2"]
  },
  {
    "name": "Death Palm",
    "input": "ub+1+2",
    "hit_level": "!",
    "damage": "70",
    "startup": "i79~82",
    "block": "",
    "hit": "+50g (+19)",
    "counter": "",
    "note": "",
    "alternateInputs": ["ub+1+2"]
  },
  {
    "name": "Leaping Hammer Fist",
    "input": "u+2",
    "hit_level": "m",
    "damage": "25",
    "startup": "i38~40",
    "block": "+2",
    "hit": "+10",
    "counter": "",
    "note": "\njs",
    "alternateInputs": ["u+2"]
  },
  {
    "name": "Eagle Claw",
    "input": "uf+1",
    "hit_level": "m",
    "damage": "12",
    "startup": "i18~19",
    "block": "-5",
    "hit": "+4",
    "counter": "",
    "note": "\njs\n+12 on crouching opponent\nAlternate input with uf or u\n",
    "alternateInputs": ["uf+1"]
  },
  {
    "name": "Evading Palm Strike",
    "input": "uf+2",
    "hit_level": "m",
    "damage": "18",
    "startup": "i18",
    "block": "-10",
    "hit": "+3",
    "counter": "",
    "note": "",
    "alternateInputs": ["uf+2"]
  },
  {
    "name": "Side Swipe",
    "input": "uf+3",
    "hit_level": "m",
    "damage": "20",
    "startup": "i22~23",
    "block": "-1",
    "hit": "+22d",
    "counter": "",
    "note": "\njs\nAlternate input with uf or u\n",
    "alternateInputs": ["uf+3"]
  },
  {
    "name": "Soaring Eagle",
    "input": "uf+4",
    "hit_level": "m",
    "damage": "13",
    "startup": "i15~17",
    "block": "-13",
    "hit": "+33a (+23)",
    "counter": "",
    "note": "\njs\nAlternate input with uf or u\n",
    "alternateInputs": ["uf+4"]
  },
  {
    "name": "",
    "input": "uf+3+4",
    "hit_level": "m,h,h",
    "damage": "10,10,7",
    "startup": "i24,4,3",
    "block": "-14",
    "hit": "+25a (+18)",
    "counter": "",
    "note": "\ncs, then js",
    "alternateInputs": ["uf+3+4"]
  },
  {
    "name": "Assassin's Bow",
    "input": "uf+3+4,3",
    "hit_level": "m,h,h,h",
    "damage": "10,10,7,11",
    "startup": ",i17~18",
    "block": "-6",
    "hit": "+70a (+54)",
    "counter": "",
    "note": "\n\nBalcony Break\n\nTornado\nCombo from 1st hit\n",
    "alternateInputs": ["uf+3+4,3"]
  },
  {
    "name": "Delayed Rising Toe Kick",
    "input": "uf,n,4",
    "hit_level": "m",
    "damage": "20",
    "startup": "i23~25",
    "block": "-13",
    "hit": "+32a (+22)",
    "counter": "",
    "note": "\njs",
    "alternateInputs": ["uf,n,4"]
  },
  {
    "name": "Exploding Dagger",
    "input": "f,F+2",
    "hit_level": "m",
    "damage": "25",
    "startup": "i18~19",
    "block": "-9",
    "hit": "+16a (+7)",
    "counter": "",
    "note": "\n\nHeat Engager\n\n\nHeat Dash +5, +36a (+26)\n\n\nBalcony Break\n",
    "alternateInputs": ["f,F+2"]
  },
  {
    "name": "Tremor Stomp",
    "input": "f,F+3",
    "hit_level": "m",
    "damage": "35",
    "startup": "i32~33",
    "block": "+8c",
    "hit": "+8c",
    "counter": "",
    "note": "\nChip damage on block\nTransition to +4c +4c STC with f\n",
    "alternateInputs": ["f,F+3"]
  },
  {
    "name": "",
    "input": "f,F+4",
    "hit_level": "m",
    "damage": "15",
    "startup": "i19~20",
    "block": "-15",
    "hit": "+30a (+20)",
    "counter": "",
    "note": "",
    "alternateInputs": ["f,F+4"]
  },
  {
    "name": "Spreading Wings",
    "input": "f,F+4,3",
    "hit_level": "m,m",
    "damage": "15,21",
    "startup": "i20~21",
    "block": "-14",
    "hit": "+32a (+25)",
    "counter": "",
    "note": "\njs\nMove can be powered up by delaying input (25 damage)\n",
    "alternateInputs": ["f,F+4,3"]
  },
  {
    "name": "Nian Zhang Mie Ba",
    "input": "f,F+1+2",
    "hit_level": "m",
    "damage": "25",
    "startup": "i24~25",
    "block": "-9",
    "hit": "+16a",
    "counter": "",
    "note": "\n\nBalcony Break\nHold 1+2 to power up and deal more chip damage on block\n",
    "alternateInputs": ["f,F+1+2"]
  },
  {
    "name": "Nian Zhang Mie Ba (charged)",
    "input": "f,F+1+2*",
    "hit_level": "m",
    "damage": "30",
    "startup": "i39",
    "block": "+6",
    "hit": "+22a (+12)",
    "counter": "",
    "note": "\n\nBalcony Break\n\nWall Crush +18g\n\nBecomes  Essence of Nian Zhang Mie Ba in Heat\n",
    "alternateInputs": ["f,F+1+2*"]
  },
  {
    "name": "Falcon's Beak",
    "input": "b,f+1",
    "hit_level": "m",
    "damage": "25",
    "startup": "i25~26",
    "block": "-15",
    "hit": "+10d (+1)",
    "counter": "+44a",
    "note": "",
    "alternateInputs": ["b,f+1"]
  },
  {
    "name": "Severing Sword",
    "input": "f,f,F+3",
    "hit_level": "m",
    "damage": "30",
    "startup": "i20~25",
    "block": "+6",
    "hit": "+13d (+3)",
    "counter": "",
    "note": "\njs\n\nBalcony Break\nChip damage on block\n",
    "alternateInputs": ["f,f,F+3"]
  },
  {
    "name": "Lingering Shadow",
    "input": "qcf",
    "hit_level": "",
    "damage": "",
    "startup": "",
    "block": "",
    "hit": "",
    "counter": "",
    "note": "\ncs\nD,df to enter crouching state\n",
    "alternateInputs": ["qcf"]
  },
  {
    "name": "Landslide",
    "input": "qcf1",
    "hit_level": "L",
    "damage": "23",
    "startup": "i22~23",
    "block": "-14",
    "hit": "+2",
    "counter": "+31a",
    "note": "\ncsHead",
    "alternateInputs": ["qcf1"]
  },
  {
    "name": "Mountain Crusher",
    "input": "qcf2",
    "hit_level": "m",
    "damage": "25",
    "startup": "i22~23",
    "block": "-14",
    "hit": "+35a (+25)",
    "counter": "",
    "note": "\n\nTornado\n",
    "alternateInputs": ["qcf2"]
  },
  {
    "name": "Yan Wang's Wrath",
    "input": "qcf1+2",
    "hit_level": "m",
    "damage": "21",
    "startup": "i16~17",
    "block": "0c",
    "hit": "+7c",
    "counter": "+23d",
    "note": "Head",
    "alternateInputs": ["qcf1+2"]
  },
  {
    "name": "",
    "input": "qcf3+4",
    "hit_level": "",
    "damage": "",
    "startup": "",
    "block": "",
    "hit": "",
    "counter": "",
    "note": "Transitions to STC",
    "alternateInputs": ["qcf3+4"]
  },
  {
    "name": "Silent Arrow",
    "input": "FC df+1",
    "hit_level": "L",
    "damage": "19",
    "startup": "i21~22",
    "block": "-13c",
    "hit": "-2",
    "counter": "+13",
    "note": "",
    "alternateInputs": ["FC df+1"]
  },
  {
    "name": "Monkey Strike",
    "input": "FC df+2",
    "hit_level": "m",
    "damage": "21",
    "startup": "i18",
    "block": "-14",
    "hit": "+55a",
    "counter": "",
    "note": "",
    "alternateInputs": ["FC df+2"]
  },
  {
    "name": "",
    "input": "FC df+4",
    "hit_level": "L",
    "damage": "10",
    "startup": "i19~20",
    "block": "-8c",
    "hit": "+3b",
    "counter": "",
    "note": "\nCan be input with D,df+4\n",
    "alternateInputs": ["FC df+4"]
  },
  {
    "name": "Xuan Jiao Xian Yan Shou",
    "input": "FC df+4,1",
    "hit_level": "L,h",
    "damage": "10,15",
    "startup": "i20~21",
    "block": "-2",
    "hit": "+6",
    "counter": "",
    "note": "\nCombo from 1st attack\n",
    "alternateInputs": ["FC df+4,1"]
  },
  {
    "name": "",
    "input": "ws1",
    "hit_level": "m",
    "damage": "13",
    "startup": "i13",
    "block": "-1",
    "hit": "+5",
    "counter": "",
    "note": "",
    "alternateInputs": ["ws1"]
  },
  {
    "name": "",
    "input": "ws1,2",
    "hit_level": "m,m",
    "damage": "13,16",
    "startup": ",i9",
    "block": "-10",
    "hit": "+1",
    "counter": "",
    "note": "\nJail from 1st attack\n",
    "alternateInputs": ["ws1,2"]
  },
  {
    "name": "Dancing Dragon",
    "input": "ws1,2,1",
    "hit_level": "m,m,m",
    "damage": "13,16,20",
    "startup": "i17~18",
    "block": "-12",
    "hit": "+12d (+3)",
    "counter": "+32d (+24)",
    "note": "\n\nBalcony Break\nMove can be delayed\n",
    "alternateInputs": ["ws1,2,1"]
  },
  {
    "name": "Dancing Scorpion Sting",
    "input": "ws1,3",
    "hit_level": "m,h",
    "damage": "13,20",
    "startup": "i22~23",
    "block": "-6",
    "hit": "+4c",
    "counter": "+20d",
    "note": "\nCombo from 1st CH\nMove can be delayed\n",
    "alternateInputs": ["ws1,3"]
  },
  {
    "name": "Adamantine Uppercut",
    "input": "ws2",
    "hit_level": "m",
    "damage": "17",
    "startup": "i15~16",
    "block": "-7",
    "hit": "+24d",
    "counter": "+78a (+62)",
    "note": "\n\nBalcony Break\n\nTornado (CH Only)\n",
    "alternateInputs": ["ws2"]
  },
  {
    "name": "Bow Kick",
    "input": "ws3",
    "hit_level": "m",
    "damage": "15",
    "startup": "i15~16",
    "block": "-12",
    "hit": "+33a (+23)",
    "counter": "",
    "note": "",
    "alternateInputs": ["ws3"]
  },
  {
    "name": "Rising Heel Kick",
    "input": "ws4",
    "hit_level": "m",
    "damage": "18",
    "startup": "i11~12",
    "block": "-7",
    "hit": "+7",
    "counter": "+29d",
    "note": "",
    "alternateInputs": ["ws4"]
  },
  {
    "name": "Push Hands",
    "input": "ws1+2",
    "hit_level": "m",
    "damage": "20",
    "startup": "i23~24",
    "block": "-9",
    "hit": "+3",
    "counter": "",
    "note": "\nps",
    "alternateInputs": ["ws1+2"]
  },
  {
    "name": "Shifting Clouds",
    "input": "f+3+4",
    "hit_level": "",
    "damage": "",
    "startup": "",
    "block": "",
    "hit": "",
    "counter": "",
    "note": "\nps",
    "alternateInputs": ["f+3+4"]
  },
  {
    "name": "Bao Dan Po",
    "input": "STC 1",
    "hit_level": "m",
    "damage": "20",
    "startup": "i20~21",
    "block": "-15",
    "hit": "+30a",
    "counter": "",
    "note": "\npc\nAbsorb an attack to power up and deal more chip damage on block\n",
    "alternateInputs": ["STC 1"]
  },
  {
    "name": "Driller Hook Backhand",
    "input": "STC 2",
    "hit_level": "h",
    "damage": "15",
    "startup": "i14~15",
    "block": "-3",
    "hit": "+6",
    "counter": "",
    "note": "\nEnter BT with b\n",
    "alternateInputs": ["STC 2"]
  },
  {
    "name": "Scorpion Sting",
    "input": "STC 3",
    "hit_level": "h",
    "damage": "25",
    "startup": "i22~23",
    "block": "+3b",
    "hit": "+23d",
    "counter": "",
    "note": "\n\nHoming\n\nBalcony Break\nChip damage on block\n",
    "alternateInputs": ["STC 3"]
  },
  {
    "name": "Jin Bu Zhen",
    "input": "STC 4",
    "hit_level": "L",
    "damage": "20",
    "startup": "i20",
    "block": "-13",
    "hit": "+3",
    "counter": "",
    "note": "",
    "alternateInputs": ["STC 4"]
  },
  {
    "name": "Pummeling Fists",
    "input": "STC 1+2",
    "hit_level": "m",
    "damage": "20",
    "startup": "i18",
    "block": "-9c",
    "hit": "+17d",
    "counter": "",
    "note": "",
    "alternateInputs": ["STC 1+2"]
  },
  {
    "name": "Falcon Beak's Snare",
    "input": "STC F+3+4",
    "hit_level": "m",
    "damage": "21",
    "startup": "i18",
    "block": "",
    "hit": "+53a",
    "counter": "",
    "note": "\nps\nAbsorbs two attacks for a follow up attack\n",
    "alternateInputs": ["STC F+3+4"]
  },
  {
    "name": "Deceptive Step",
    "input": "b+3+4",
    "hit_level": "",
    "damage": "",
    "startup": "",
    "block": "",
    "hit": "",
    "counter": "",
    "note": "\nEnter STC with f\n",
    "alternateInputs": ["b+3+4"]
  },
  {
    "name": "Fractured Diamond",
    "input": "KNP 1",
    "hit_level": "L",
    "damage": "20",
    "startup": "i20~21",
    "block": "-13c",
    "hit": "+8",
    "counter": "+38d",
    "note": "",
    "alternateInputs": ["KNP 1"]
  },
  {
    "name": "Fei He Zhang",
    "input": "KNP 2",
    "hit_level": "h",
    "damage": "20",
    "startup": "i14",
    "block": "-9",
    "hit": "+17",
    "counter": "",
    "note": "\n\nHeat Engager\n\n\nBalcony Break\n",
    "alternateInputs": ["KNP 2"]
  },
  {
    "name": "Rising Swallow Kick",
    "input": "KNP 3",
    "hit_level": "m",
    "damage": "20",
    "startup": "i22~23",
    "block": "-14",
    "hit": "+77a (+55)",
    "counter": "",
    "note": "\n\nTornado\n",
    "alternateInputs": ["KNP 3"]
  },
  {
    "name": "",
    "input": "KNP 4",
    "hit_level": "L",
    "damage": "10",
    "startup": "i18",
    "block": "-31c",
    "hit": "-4",
    "counter": "",
    "note": "",
    "alternateInputs": ["KNP 4"]
  },
  {
    "name": "Xuan Tui Strike",
    "input": "KNP 4,1+2",
    "hit_level": "L,h",
    "damage": "10,24",
    "startup": "i28",
    "block": "-6",
    "hit": "+30a (+20)",
    "counter": "",
    "note": "\n\nBalcony Break\nCombo from 1st attack\n",
    "alternateInputs": ["KNP 4,1+2"]
  },
  {
    "name": "",
    "input": "KNP 3+4",
    "hit_level": "M",
    "damage": "30",
    "startup": "i31~34",
    "block": "-7",
    "hit": "-3d",
    "counter": "",
    "note": "",
    "alternateInputs": ["KNP 3+4"]
  },
  {
    "name": "Leaping Lion",
    "input": "KNP 3+4,3+4",
    "hit_level": "M,m",
    "damage": "30",
    "startup": "i39~42",
    "block": "",
    "hit": "",
    "counter": "",
    "note": "",
    "alternateInputs": ["KNP 3+4,3+4"]
  },
  {
    "name": "Zhuan Shen Huan Wu",
    "input": "b+3~4",
    "hit_level": "",
    "damage": "",
    "startup": "",
    "block": "",
    "hit": "",
    "counter": "",
    "note": "\nEnter STC with F\n",
    "alternateInputs": ["b+3~4"]
  },
  {
    "name": "Backfist",
    "input": "BT 1",
    "hit_level": "h",
    "damage": "12",
    "startup": "i12",
    "block": "-3",
    "hit": "+14g",
    "counter": "",
    "note": "",
    "alternateInputs": ["BT 1"]
  },
  {
    "name": "Slashing Tiger",
    "input": "BT 2",
    "hit_level": "m",
    "damage": "23",
    "startup": "i19~21",
    "block": "-13",
    "hit": "+17",
    "counter": "",
    "note": "\npc\n\nHeat Engager\n\nAbsorb an attack to power up and deal more damage on block\n",
    "alternateInputs": ["BT 2"]
  },
  {
    "name": "Tremor Stomp",
    "input": "BT 3",
    "hit_level": "m",
    "damage": "35",
    "startup": "i32~33",
    "block": "+8c",
    "hit": "+8c",
    "counter": "",
    "note": "\nChip damage on block\nTransition to STC with f\n",
    "alternateInputs": ["BT 3"]
  },
  {
    "name": "Hustle Elbow",
    "input": "BT 1+2",
    "hit_level": "m",
    "damage": "20",
    "startup": "i16~17",
    "block": "-3",
    "hit": "+8",
    "counter": "+41d (+33)",
    "note": "\n\nBalcony Break (CH only)\n",
    "alternateInputs": ["BT 1+2"]
  },
  {
    "name": "Reverse Mighty Sweep Kick",
    "input": "BT d+3",
    "hit_level": "L",
    "damage": "20",
    "startup": "i18~20",
    "block": "=26c",
    "hit": "-3",
    "counter": "+70a (+54)",
    "note": "\nHas clean hit effect\n",
    "alternateInputs": ["BT d+3"]
  },
  {
    "name": "Enlighted Yellow Dragon Palm",
    "input": "in rage df+1+2",
    "hit_level": "t",
    "damage": "55",
    "startup": "i20",
    "block": "-15",
    "hit": "+0d",
    "counter": "",
    "note": "\nRage Art\nErases opponent's recoverable health on hit\nDamage increases with lower health",
    "alternateInputs": ["in rage df+1+2"]
  },
  {
    "name": "Taunt",
    "input": "1+3+4",
    "hit_level": "",
    "damage": "",
    "startup": "",
    "block": "",
    "hit": "",
    "counter": "",
    "note": "",
    "alternateInputs": ["1+3+4"]
  },
  {
    "name": "Ki Charge",
    "input": "1+2+3+4",
    "hit_level": "",
    "damage": "",
    "startup": "",
    "block": "",
    "hit": "",
    "counter": "",
    "note": "",
    "alternateInputs": ["1+2+3+4"]
  },
  {
    "name": "Hidden Intentions",
    "input": "SS 2",
    "hit_level": "h",
    "damage": "18",
    "startup": "i15",
    "block": "+3",
    "hit": "+9b",
    "counter": "+31d",
    "note": "\n\nHoming\n",
    "alternateInputs": ["SS 2"]
  },
  {
    "name": "swift Sweep Kick",
    "input": "SS 4",
    "hit_level": "L",
    "damage": "19",
    "startup": "i21~22",
    "block": "-31c",
    "hit": "+8 (-8)",
    "counter": "+72a (+56)",
    "note": "\nHas a clean hit effect\n",
    "alternateInputs": ["SS 4"]
  },
  {
    "name": "Enlightened Circle",
    "input": "SS 1+2",
    "hit_level": "m",
    "damage": "24",
    "startup": "i22~23",
    "block": "+1",
    "hit": "+21d (+12)",
    "counter": "",
    "note": "\n\nBalcony Break\nChip damage on block\n",
    "alternateInputs": ["SS 1+2"]
  },
  {
    "name": "Spring Up",
    "input": "Grounded Face Up B+3+4",
    "hit_level": "m",
    "damage": "20",
    "startup": "i30~33",
    "block": "",
    "hit": "+28d (+18)",
    "counter": "",
    "note": "\n\nBalcony Break\n",
    "alternateInputs": ["Grounded Face Up B+3+4"]
  },
  {
    "name": "Thunder Stomp",
    "input": "OTG d+3+4",
    "hit_level": "L",
    "damage": "19",
    "startup": "i24~25",
    "block": "",
    "hit": "-2 (-10)",
    "counter": "",
    "note": "",
    "alternateInputs": ["OTG d+3+4"]
  },
  {
    "name": "Neck Twister",
    "input": "1+3",
    "hit_level": "h",
    "damage": "35",
    "startup": "Startup",
    "block": "",
    "hit": "-3",
    "counter": "",
    "note": "\nThrow break 1 or 2\n",
    "alternateInputs": ["1+3"]
  },
  {
    "name": "Serpent Slayer",
    "input": "2+4",
    "hit_level": "h",
    "damage": "35",
    "startup": "Startup",
    "block": "",
    "hit": "0",
    "counter": "",
    "note": "\nThrow break 1 or 2\n",
    "alternateInputs": ["2+4"]
  },
  {
    "name": "Jaws of Death",
    "input": "Left Throw",
    "hit_level": "h",
    "damage": "40",
    "startup": "Startup",
    "block": "",
    "hit": "-6",
    "counter": "",
    "note": "\nThrow break 1\n",
    "alternateInputs": ["Left Throw"]
  },
  {
    "name": "Wandering Soul",
    "input": "Right Throw",
    "hit_level": "h",
    "damage": "40",
    "startup": "Startup",
    "block": "",
    "hit": "-4",
    "counter": "",
    "note": "\nThrow break 2\n",
    "alternateInputs": ["Right Throw"]
  },
  {
    "name": "Violent Storm",
    "input": "Back Throw",
    "hit_level": "h",
    "damage": "50",
    "startup": "Startup",
    "block": "",
    "hit": "-4",
    "counter": "",
    "note": "\nCannot break throw\n",
    "alternateInputs": ["Back Throw"]
  },
  {
    "name": "Kunlun Avalanche",
    "input": "uf+1+2",
    "hit_level": "h",
    "damage": "40",
    "startup": "Startup",
    "block": "",
    "hit": "0",
    "counter": "",
    "note": "\n\nSpike\nThrow break 1+2\n",
    "alternateInputs": ["uf+1+2"]
  },
  {
    "name": "Pao Lau Impaler",
    "input": "BT 1+4_2+3",
    "hit_level": "h",
    "damage": "45",
    "startup": "Startup",
    "block": "",
    "hit": "-5",
    "counter": "",
    "note": "\nThrow break 1+2\n",
    "alternateInputs": ["BT 1+4_2+3"]
  },
  {
    "name": "Attack Reversal",
    "input": "b1+3_2+4",
    "hit_level": "",
    "damage": "25",
    "startup": "",
    "block": "",
    "hit": "",
    "counter": "",
    "note": "\nps\nTimed with opponent punch\n",
    "alternateInputs": ["b1+3_2+4"]
  }
]
