[
  {
    "name": "Heat Burst",
    "input": "2+3",
    "hit_level": "m",
    "damage": "[12;12]",
    "startup": "i16",
    "block": "+1",
    "hit": "+2c",
    "counter": "",
    "alternateInputs": [
      "2+3"
    ],
    "categories": [
      "powercrush"
    ],
    "notes": [
      "Heat Burst",
      "Cancel to r45 with b,b",
      "3 chip damage on block",
      "12 chip damage on hit",
      "Only deals recoverable damage",
      "Cannot cause a K.O."
    ]
  },
  {
    "name": "Ultimo Jaguar",
    "input": "in heat 2+3",
    "hit_level": "m,t",
    "damage": "20,40",
    "startup": "i17",
    "block": "+12",
    "hit": "+0d",
    "counter": "",
    "alternateInputs": [
      "in heat 2+3"
    ],
    "categories": [
      "throw",
      "powercrush"
    ],
    "notes": [
      "Heat Smash",
      "Floor Break",
      "Shifts to JGR on block (without heat).",
      "Hold b to cancel shift, becomes +7 on block.",
      "Beats all Power Crush armor, hits OTG."
    ]
  },
  {
    "name": "Elbow Impact",
    "input": "f+2,1",
    "hit_level": "m,h",
    "damage": "12,25",
    "startup": "i15~16",
    "block": "-9",
    "hit": "+16a",
    "counter": "",
    "alternateInputs": [
      "f+2,1"
    ],
    "categories": [],
    "notes": [
      "Heat Engager",
      "Heat Dash +5 on block, +36a(+26a) on hit.",
      "Balcony Break",
      "Combo from 1st hit with 4F delay",
      "Move can be delayed by 10F",
      "Input can be delayed by 12F"
    ]
  },
  {
    "name": "Shoulder Tackle",
    "input": "f+2+3",
    "hit_level": "m",
    "damage": "27",
    "startup": "i20~24",
    "block": "-9",
    "hit": "+8a(-1a)",
    "counter": "",
    "alternateInputs": [
      "f+2+3"
    ],
    "categories": [],
    "notes": [
      "Heat Engager",
      "Heat Dash +5 on block, +36a(+26a) on hit.",
      "Balcony Break"
    ]
  },
  {
    "name": "Muscle Armor > Emerald Elbow",
    "input": "db+1+2,2",
    "hit_level": "m,t",
    "damage": "15,20",
    "startup": "i15",
    "block": "-9",
    "hit": "+8g",
    "counter": "",
    "alternateInputs": [
      "db+1+2,2"
    ],
    "categories": [
      "throw",
      "powercrush"
    ],
    "notes": [
      "Heat Engager",
      "Heat Dash +5 on block, +67a(+50a) on hit.",
      "Effective startup is i32",
      "+35g on heat engager hit",
      "Shifts to throw on front grounded hit.",
      "-5 on block after absorbing an attack with muscle armor.",
      "6 chip damage on block after absorbing an attack with muscle armor."
    ]
  },
  {
    "name": "Rapid King Onslaught",
    "input": "JGR 1+3_2+4",
    "hit_level": "t",
    "damage": "45",
    "startup": "i23",
    "block": "",
    "hit": "+1d",
    "counter": "",
    "alternateInputs": [
      "JGR 1+3_2+4"
    ],
    "categories": [
      "throw",
      "homing"
    ],
    "notes": [
      "Heat Engager",
      "Homing",
      "Cannot throw break. Cannot heat dash.",
      "Restores some Heat Gauge in Heat.",
      "Opponent recovers in FUFA.",
      "Sometimes written RKO"
    ]
  },
  {
    "name": "Freedom Face Buster (Pedigree)",
    "input": "d+1+4",
    "hit_level": "t(c)",
    "damage": "35",
    "startup": "i12~13",
    "block": "",
    "hit": "+0d",
    "counter": "",
    "alternateInputs": [
      "d+1+4"
    ],
    "categories": [
      "throw"
    ],
    "notes": [
      "Heat Engager",
      "Crouch throw, cannot throw break.",
      "Can also be done by db+1+4 and in FC too.",
      "Restores some Heat Gauge in Heat.",
      "Cannot heat dash.Opponent recovers in FDFA."
    ]
  },
  {
    "name": "Running Elbow Smash (Heat)",
    "input": "in heat JGR 1",
    "hit_level": "m",
    "damage": "21",
    "startup": "i16~17",
    "block": "-8",
    "hit": "+75a(+59)",
    "counter": "",
    "alternateInputs": [
      "in heat JGR 1"
    ],
    "categories": [],
    "notes": [
      "6 chip damage on block",
      "Partially uses remaining Heat time."
    ]
  },
  {
    "name": "Jaguar Axe (Heat)",
    "input": "in heat JGR 2",
    "hit_level": "h",
    "damage": "26",
    "startup": "i18~19",
    "block": "+6",
    "hit": "+4a",
    "counter": "",
    "alternateInputs": [
      "in heat JGR 2"
    ],
    "categories": [],
    "notes": [
      "Wall Crush +18gc on block",
      "13 chip damage on block.",
      "Forces crouching at +18c on wall crush.",
      "Partially uses remaining Heat time."
    ]
  },
  {
    "name": "Left Jab",
    "input": "1",
    "hit_level": "h",
    "damage": "5",
    "startup": "i10",
    "block": "+1",
    "hit": "+8",
    "counter": "",
    "alternateInputs": [
      "1"
    ],
    "categories": [],
    "notes": [
      "Recovers 2f faster on hit or block (t27 r17)"
    ]
  },
  {
    "name": "Palm Strike",
    "input": "1,2",
    "hit_level": "h,h",
    "damage": "5,15",
    "startup": "i10~12",
    "block": "-3",
    "hit": "+8",
    "counter": "",
    "alternateInputs": [
      "1,2"
    ],
    "categories": [],
    "notes": [
      "Combo from 1st hit with 6F delay",
      "Jail from 1st block with 5F delay"
    ]
  },
  {
    "name": "Palm Strike > Head Jammer",
    "input": "1,2,2+4",
    "hit_level": "h,h,t",
    "damage": "5,15,30",
    "startup": "i30",
    "block": "",
    "hit": "+1d",
    "counter": "",
    "alternateInputs": [
      "1,2,2+4"
    ],
    "categories": [
      "throw"
    ],
    "notes": [
      "Throw break 2."
    ]
  },
  {
    "name": "Palm Strike > V Driver",
    "input": "1,2,d+2+4",
    "hit_level": "h,h,t(c)",
    "damage": "5,15,35",
    "startup": "i27",
    "block": "",
    "hit": "+1d",
    "counter": "",
    "alternateInputs": [
      "1,2,d+2+4"
    ],
    "categories": [
      "throw"
    ],
    "notes": [
      "Floor Break",
      "Crouch throw, cannot throw break.",
      "Opponent recovers in FDFA."
    ]
  },
  {
    "name": "Palm Strike Uppercut",
    "input": "1,2,1",
    "hit_level": "h,h,m",
    "damage": "5,15,10",
    "startup": "i24~25",
    "block": "-4",
    "hit": "+5s",
    "counter": "+10s",
    "alternateInputs": [
      "1,2,1"
    ],
    "categories": [],
    "notes": [
      "Forces standing on hit.",
      "Move can be delayed by 9F",
      "Starter of 10 Strings, 3rd~5th hits are combo."
    ]
  },
  {
    "name": "Palm Strike Uppercut > Suplex",
    "input": "1,2,1,2+4",
    "hit_level": "h,h,m,t",
    "damage": "5,15,10,40",
    "startup": "i26~28",
    "block": "",
    "hit": "+0d",
    "counter": "",
    "alternateInputs": [
      "1,2,1,2+4"
    ],
    "categories": [
      "throw"
    ],
    "notes": [
      "Throw break 2."
    ]
  },
  {
    "name": "Palm Strike Uppercut > V Driver",
    "input": "1,2,1,d+2+4",
    "hit_level": "h,h,m,t(c)",
    "damage": "5,15,10,35",
    "startup": "i28~30",
    "block": "",
    "hit": "+1d",
    "counter": "",
    "alternateInputs": [
      "1,2,1,d+2+4"
    ],
    "categories": [
      "throw"
    ],
    "notes": [
      "Floor Break",
      "Crouch throw, cannot throw break.",
      "Opponent recovers in FDFA."
    ]
  },
  {
    "name": "Right Jab",
    "input": "2",
    "hit_level": "h",
    "damage": "10",
    "startup": "i10",
    "block": "+1",
    "hit": "+7",
    "counter": "",
    "alternateInputs": [
      "2"
    ],
    "categories": [],
    "notes": [
      ""
    ]
  },
  {
    "name": "Right Jab > Uppercut",
    "input": "2,1",
    "hit_level": "h,m",
    "damage": "10,15",
    "startup": "i23~24",
    "block": "-3",
    "hit": "+8",
    "counter": "",
    "alternateInputs": [
      "2,1"
    ],
    "categories": [],
    "notes": [
      "Forces standing on hit.",
      "Combo from 1st hit."
    ]
  },
  {
    "name": "Left Kick",
    "input": "3",
    "hit_level": "h",
    "damage": "25",
    "startup": "i17",
    "block": "-14",
    "hit": "+17a",
    "counter": "",
    "alternateInputs": [
      "3"
    ],
    "categories": [],
    "notes": [
      "Balcony Break",
      "Tracks left side but unsafe."
    ]
  },
  {
    "name": "Right Kick",
    "input": "4",
    "hit_level": "h",
    "damage": "20",
    "startup": "i13",
    "block": "-5",
    "hit": "+6",
    "counter": "+31d",
    "alternateInputs": [
      "4"
    ],
    "categories": [],
    "notes": [
      "Knocks down on CH for dash OTG throw.",
      "Sometimes written Magic 4"
    ]
  },
  {
    "name": "",
    "input": "1+2",
    "hit_level": "m",
    "damage": "17",
    "startup": "i18",
    "block": "-11",
    "hit": "-2s",
    "counter": "+0s",
    "alternateInputs": [
      "1+2"
    ],
    "categories": [],
    "notes": [
      "Forces standing on hit.",
      "Shifts into backturn stance."
    ]
  },
  {
    "name": "Head Spinner",
    "input": "1+2,1",
    "hit_level": "m,m",
    "damage": "17,21",
    "startup": "i22",
    "block": "-13/-18",
    "hit": "+12a(+3)/-9",
    "counter": "",
    "alternateInputs": [
      "1+2,1"
    ],
    "categories": [],
    "notes": [
      "Balcony Break",
      "Combo from 1st hit with 3F delay",
      "Interrupt with i5 from 1st block",
      "Hold back during 2nd hit to feint",
      "Input can be delayed by 3F",
      "Move cannot be delayed"
    ]
  },
  {
    "name": "Brutal Sting",
    "input": "1+2,3",
    "hit_level": "m,h",
    "damage": "17,25",
    "startup": "i24~25",
    "block": "-3",
    "hit": "+12a(+3)",
    "counter": "",
    "alternateInputs": [
      "1+2,3"
    ],
    "categories": [],
    "notes": [
      "Balcony Break",
      "Tornado",
      "Combo from 1st hit with 3F delay",
      "Combo from 1st CH with 5F delay",
      "Move can be delayed by 4F",
      "Input can be delayed by 5F"
    ]
  },
  {
    "name": "",
    "input": "f+2",
    "hit_level": "m",
    "damage": "12",
    "startup": "i15~16",
    "block": "-11",
    "hit": "+2s",
    "counter": "",
    "alternateInputs": [
      "f+2"
    ],
    "categories": [],
    "notes": [
      "Forces standing on hit?"
    ]
  },
  {
    "name": "",
    "input": "f+2,d+1",
    "hit_level": "m,m",
    "damage": "12,15",
    "startup": "i22",
    "block": "-13c",
    "hit": "+2c",
    "counter": "",
    "alternateInputs": [
      "f+2,d+1"
    ],
    "categories": [],
    "notes": [
      "Floor Break",
      "Move can be delayed by 10F",
      "Input can be delayed by 12F"
    ]
  },
  {
    "name": "Jaguar Smash Combo",
    "input": "f+2,d+1,2",
    "hit_level": "m,m,m",
    "damage": "12,15,16",
    "startup": "i22~23",
    "block": "-15",
    "hit": "+27a(+17)",
    "counter": "",
    "alternateInputs": [
      "f+2,d+1,2"
    ],
    "categories": [],
    "notes": [
      "Combo from 2nd hit with 13F delay",
      "Move can be delayed by 10F",
      "Input can be delayed by 13F",
      "Jail from 2nd block with no delay"
    ]
  },
  {
    "name": "Front Kick",
    "input": "f+3",
    "hit_level": "m",
    "damage": "18",
    "startup": "i15~16",
    "block": "-8",
    "hit": "+1",
    "counter": "+9s",
    "alternateInputs": [
      "f+3"
    ],
    "categories": [],
    "notes": [
      "Only forces standing on CH."
    ]
  },
  {
    "name": "Front Kick > DDT",
    "input": "f+3:1+2",
    "hit_level": "m,t",
    "damage": "18,20",
    "startup": "i15~16",
    "block": "",
    "hit": "-5d",
    "counter": "",
    "alternateInputs": [
      "f+3:1+2"
    ],
    "categories": [
      "throw"
    ],
    "notes": [
      "Input 1+2 during frames 16-19 of f+3",
      "Shifts to throw on front grounded hit."
    ]
  },
  {
    "name": "Rolling Sobat",
    "input": "f+4",
    "hit_level": "m",
    "damage": "25",
    "startup": "i18~20",
    "block": "-9",
    "hit": "+12a(+3)",
    "counter": "",
    "alternateInputs": [
      "f+4"
    ],
    "categories": [
      "homing"
    ],
    "notes": [
      "Balcony Break",
      "Homing"
    ]
  },
  {
    "name": "Shadow Lariat",
    "input": "f+1+2",
    "hit_level": "h",
    "damage": "23",
    "startup": "i16~17",
    "block": "+0",
    "hit": "+10d",
    "counter": "",
    "alternateInputs": [
      "f+1+2"
    ],
    "categories": [],
    "notes": [
      ""
    ]
  },
  {
    "name": "Body Check",
    "input": "f+1+4",
    "hit_level": "m",
    "damage": "21",
    "startup": "i17~19",
    "block": "+3",
    "hit": "+7s",
    "counter": "",
    "alternateInputs": [
      "f+1+4"
    ],
    "categories": [],
    "notes": [
      "Forces standing on hit."
    ]
  },
  {
    "name": "",
    "input": "df+1",
    "hit_level": "m",
    "damage": "15",
    "startup": "i14~15",
    "block": "-1",
    "hit": "+3s",
    "counter": "",
    "alternateInputs": [
      "df+1"
    ],
    "categories": [],
    "notes": [
      "Forces standing on hit."
    ]
  },
  {
    "name": "Elbow Sting",
    "input": "df+1,2",
    "hit_level": "m,m",
    "damage": "15,15",
    "startup": "i20~21",
    "block": "-10",
    "hit": "+5s",
    "counter": "",
    "alternateInputs": [
      "df+1,2"
    ],
    "categories": [],
    "notes": [
      "Combo from 1st hit with 5F delay",
      "Combo from 1st CH with 9F delay",
      "Jail from 1st block with 5F delay",
      "Move can be delayed by 11F",
      "Input can be delayed by 13F"
    ]
  },
  {
    "name": "",
    "input": "df+2",
    "hit_level": "m",
    "damage": "12",
    "startup": "i13",
    "block": "-6",
    "hit": "+4s",
    "counter": "",
    "alternateInputs": [
      "df+2"
    ],
    "categories": [],
    "notes": [
      "Forces standing on hit."
    ]
  },
  {
    "name": "Double Hook Disaster",
    "input": "df+2,1",
    "hit_level": "m,h",
    "damage": "12,15",
    "startup": "i20~21",
    "block": "-4",
    "hit": "+24a",
    "counter": "",
    "alternateInputs": [
      "df+2,1"
    ],
    "categories": [],
    "notes": [
      "Combo from 1st CH with 12F delay",
      "Move can be delayed by 13F"
    ]
  },
  {
    "name": "",
    "input": "df+3",
    "hit_level": "m",
    "damage": "17",
    "startup": "i14",
    "block": "-9",
    "hit": "+6s",
    "counter": "",
    "alternateInputs": [
      "df+3"
    ],
    "categories": [],
    "notes": [
      "Forces standing on hit.",
      "Tracks left side."
    ]
  },
  {
    "name": "Lasso Kick",
    "input": "df+3,4",
    "hit_level": "m,h",
    "damage": "17,23",
    "startup": "i30",
    "block": "+0",
    "hit": "+28d",
    "counter": "",
    "alternateInputs": [
      "df+3,4"
    ],
    "categories": [],
    "notes": [
      "Combos on CH, otherwise opponent can duck.",
      "Available only on 1st hit or block",
      "Recovers in FDFT."
    ]
  },
  {
    "name": "",
    "input": "df+4",
    "hit_level": "l",
    "damage": "10",
    "startup": "i14~15",
    "block": "-14",
    "hit": "-3",
    "counter": "",
    "alternateInputs": [
      "df+4"
    ],
    "categories": [],
    "notes": [
      ""
    ]
  },
  {
    "name": "",
    "input": "df+4,3",
    "hit_level": "l,h",
    "damage": "10,11",
    "startup": "i22",
    "block": "-5",
    "hit": "+6",
    "counter": "",
    "alternateInputs": [
      "df+4,3"
    ],
    "categories": [],
    "notes": [
      "Combo from 1st CH"
    ]
  },
  {
    "name": "Mincer",
    "input": "df+4,3,4",
    "hit_level": "l,h,m",
    "damage": "10,11,27",
    "startup": "i28~29",
    "block": "-15",
    "hit": "+6a (-3)",
    "counter": "+47a(+16)",
    "alternateInputs": [
      "df+4,3,4"
    ],
    "categories": [],
    "notes": [
      "Balcony Break",
      "Combo from 2nd CH.",
      "Crumple on 3rd CH.",
      "Shift to r32? BT (-8, +13a (+4a), +54a (+23a)) with B",
      "Shift to backturn is 14F punishable."
    ]
  },
  {
    "name": "Mincer Low",
    "input": "df+4,3,d+4",
    "hit_level": "l,h,L",
    "damage": "10,11,20",
    "startup": "i33~35",
    "block": "-10",
    "hit": "-8a FC",
    "counter": "+22a FC",
    "alternateInputs": [
      "df+4,3,d+4"
    ],
    "categories": [],
    "notes": [
      "Recovers in crouch on hit.",
      "Otherwise recovers in FDFT."
    ]
  },
  {
    "name": "Frankensteiner",
    "input": "df+3+4",
    "hit_level": "t/s",
    "damage": "30/15",
    "startup": "i28~35",
    "block": "-12~-18",
    "hit": "+18d/-7~0",
    "counter": "",
    "alternateInputs": [
      "df+3+4"
    ],
    "categories": [
      "throw"
    ],
    "notes": [
      "Throw only when opponent standing close.",
      "Cannot throw break.",
      "Recovers in BT/FUFT on throw success/failed."
    ]
  },
  {
    "name": "",
    "input": "d+1",
    "hit_level": "s.l",
    "damage": "5",
    "startup": "i10",
    "block": "-5",
    "hit": "+6",
    "counter": "",
    "alternateInputs": [
      "d+1"
    ],
    "categories": [],
    "notes": [
      ""
    ]
  },
  {
    "name": "Jab > Uppercut",
    "input": "d+1,2",
    "hit_level": "s.l,m",
    "damage": "5,13",
    "startup": "i10,i15~17",
    "block": "-11",
    "hit": "+5s",
    "counter": "",
    "alternateInputs": [
      "d+1,2"
    ],
    "categories": [],
    "notes": [
      "Jail from 1st block",
      "Combo from 1st CH",
      "Forces standing on hit."
    ]
  },
  {
    "name": "",
    "input": "d+2",
    "hit_level": "s.l",
    "damage": "8",
    "startup": "i11",
    "block": "-4",
    "hit": "+7",
    "counter": "",
    "alternateInputs": [
      "d+2"
    ],
    "categories": [],
    "notes": [
      ""
    ]
  },
  {
    "name": "Stomp",
    "input": "d+3",
    "hit_level": "L",
    "damage": "12",
    "startup": "i17",
    "block": "-12",
    "hit": "+1",
    "counter": "",
    "alternateInputs": [
      "d+3"
    ],
    "categories": [],
    "notes": [
      "Hits OTG."
    ]
  },
  {
    "name": "",
    "input": "d+4",
    "hit_level": "l",
    "damage": "6",
    "startup": "i14",
    "block": "-15",
    "hit": "-4",
    "counter": "",
    "alternateInputs": [
      "d+4"
    ],
    "categories": [],
    "notes": [
      ""
    ]
  },
  {
    "name": "Atlas Hammer",
    "input": "d+1+2",
    "hit_level": "m",
    "damage": "21",
    "startup": "i23",
    "block": "-24",
    "hit": "+45a(+35)",
    "counter": "",
    "alternateInputs": [
      "d+1+2"
    ],
    "categories": [],
    "notes": [
      "Tornado"
    ]
  },
  {
    "name": "",
    "input": "d+3+4",
    "hit_level": "L",
    "damage": "14",
    "startup": "i16",
    "block": "-25",
    "hit": "-9",
    "counter": "",
    "alternateInputs": [
      "d+3+4"
    ],
    "categories": [],
    "notes": [
      "On CH, can access Stagger Kicks Flurry (d+3+4,4,4,4)"
    ]
  },
  {
    "name": "",
    "input": "d+3+4,4",
    "hit_level": "L,L",
    "damage": "14,7",
    "startup": "i29",
    "block": "-25",
    "hit": "-9",
    "counter": "",
    "alternateInputs": [
      "d+3+4,4"
    ],
    "categories": [],
    "notes": [
      "Combo from 1st hit on CH."
    ]
  },
  {
    "name": "Stagger Kicks",
    "input": "d+3+4,4,4",
    "hit_level": "L,L,L",
    "damage": "14,7,7",
    "startup": "i29",
    "block": "-29",
    "hit": "+7",
    "counter": "",
    "alternateInputs": [
      "d+3+4,4,4"
    ],
    "categories": [],
    "notes": [
      "Combo from 2nd hit on CH.",
      "Sometimes written Ali Kicks"
    ]
  },
  {
    "name": "Stagger Kick Spinning Uppercut",
    "input": "d+3+4,4,4,2",
    "hit_level": "L,L,L,m",
    "damage": "14,7,7,10",
    "startup": "i28",
    "block": "-15",
    "hit": "+16d(+6)",
    "counter": "",
    "alternateInputs": [
      "d+3+4,4,4,2"
    ],
    "categories": [],
    "notes": [
      "Balcony Break",
      "Combo from 1st or 2nd CH or 3rd hit"
    ]
  },
  {
    "name": "Stagger Kick Flurry",
    "input": "d+3+4,4,4,4",
    "hit_level": "L,L,L,L,L",
    "damage": "14,7,7,4,3",
    "startup": "i29,i29",
    "block": "-26",
    "hit": "+15",
    "counter": "",
    "alternateInputs": [
      "d+3+4,4,4,4"
    ],
    "categories": [],
    "notes": [
      "Only available if 1st hit on CH.",
      "Combo from 3rd hit"
    ]
  },
  {
    "name": "Corporate Elbow",
    "input": "d+2+3",
    "hit_level": "M",
    "damage": "25",
    "startup": "i30~35",
    "block": "-8",
    "hit": "+0c",
    "counter": "",
    "alternateInputs": [
      "d+2+3"
    ],
    "categories": [],
    "notes": [
      "Floor Break",
      "Sometimes written People's Elbow"
    ]
  },
  {
    "name": "Brain Chop",
    "input": "db+2",
    "hit_level": "m",
    "damage": "21",
    "startup": "i25~26",
    "block": "-5c",
    "hit": "+19a",
    "counter": "",
    "alternateInputs": [
      "db+2"
    ],
    "categories": [],
    "notes": [
      "Forces Crouching on block."
    ]
  },
  {
    "name": "Crouching Low Kick",
    "input": "db+3",
    "hit_level": "L",
    "damage": "17",
    "startup": "i23",
    "block": "-14",
    "hit": "+4c",
    "counter": "+25a",
    "alternateInputs": [
      "db+3"
    ],
    "categories": [],
    "notes": [
      "Tracks left side.",
      "Flip over on grounded hit"
    ]
  },
  {
    "name": "Low Drop Kick",
    "input": "db+4",
    "hit_level": "L",
    "damage": "20",
    "startup": "i29~31",
    "block": "-17a",
    "hit": "-3d",
    "counter": "+27d",
    "alternateInputs": [
      "db+4"
    ],
    "categories": [],
    "notes": [
      "r41 FC on hit"
    ]
  },
  {
    "name": "Muscle Armor",
    "input": "db+1+2",
    "hit_level": "",
    "damage": "",
    "startup": "",
    "block": "",
    "hit": "",
    "counter": "",
    "alternateInputs": [
      "db+1+2"
    ],
    "categories": [
      "powercrush"
    ],
    "notes": [
      "Damage taken during power crush state is recoverable",
      "Cancel into db1+2,2 (Emerald Elbow) on frames 17~60 with input 2",
      "Cancel into r30 JGR with input 3+4 on frame 35",
      "Cancel into movement or crouch or any attack on frame 40 (r40)"
    ]
  },
  {
    "name": "Muscle Armor > Jaguar Sprint",
    "input": "db+1+2,3+4",
    "hit_level": "",
    "damage": "",
    "startup": "",
    "block": "",
    "hit": "",
    "counter": "",
    "alternateInputs": [
      "db+1+2,3+4"
    ],
    "categories": [],
    "notes": [
      "Effective startup for stance moves is increased by 65 frames starting from db1+2 (Muscle Armor) startup",
      "pc7~ in heat"
    ]
  },
  {
    "name": "Quick Hook",
    "input": "b+1",
    "hit_level": "h",
    "damage": "13",
    "startup": "i12",
    "block": "-8",
    "hit": "+3",
    "counter": "+3a",
    "alternateInputs": [
      "b+1"
    ],
    "categories": [],
    "notes": [
      ""
    ]
  },
  {
    "name": "Quick Hook > Uppercut",
    "input": "b+1,2",
    "hit_level": "h,h",
    "damage": "1320",
    "startup": "i19~20",
    "block": "-13",
    "hit": "+5",
    "counter": "+70a(+54)*",
    "alternateInputs": [
      "b+1,2"
    ],
    "categories": [],
    "notes": [
      "Tornado",
      "Combo from 1st hit with 8F delay",
      "Combo from 1st CH with 10F delay",
      "Launches opponent if b+1 on CH.",
      "Move can be delayed by 6F",
      "Input can be delayed by 10F"
    ]
  },
  {
    "name": "Quick Hook > Heel Kick",
    "input": "b+1,4",
    "hit_level": "h,m",
    "damage": "1323",
    "startup": "i26~28",
    "block": "-11",
    "hit": "+1d",
    "counter": "+18(-17)*",
    "alternateInputs": [
      "b+1,4"
    ],
    "categories": [],
    "notes": [
      "Combo from 1st CH with no delay.",
      "Recovers in FUFT.",
      "Move can be delayed by 6F",
      "Input can be delayed by 10F"
    ]
  },
  {
    "name": "Chupacabra",
    "input": "b+2",
    "hit_level": "h",
    "damage": "16",
    "startup": "i14",
    "block": "-5",
    "hit": "+1",
    "counter": "",
    "alternateInputs": [
      "b+2"
    ],
    "categories": [],
    "notes": [
      ""
    ]
  },
  {
    "name": "Chupacabra > Spinning Back Elbow",
    "input": "b+2,1",
    "hit_level": "h,h",
    "damage": "16,21",
    "startup": "i20~21",
    "block": "-9",
    "hit": "+19a(+10)",
    "counter": "",
    "alternateInputs": [
      "b+2,1"
    ],
    "categories": [],
    "notes": [
      "Balcony Break",
      "Combo from 1st hit with 5F delay (buffered).",
      "Move can be delayed by 10F",
      "Input can be delayed by 15F"
    ]
  },
  {
    "name": "Chupacabra > Olympia Slam",
    "input": "b+2,4",
    "hit_level": "h,m,t",
    "damage": "16,18,20",
    "startup": "i21",
    "block": "-8",
    "hit": "+10s/+0",
    "counter": "",
    "alternateInputs": [
      "b+2,4"
    ],
    "categories": [
      "throw"
    ],
    "notes": [
      "Shifts to throw on front grounded hit.",
      "Move can be delayed by 10F",
      "Input can be delayed by 15F"
    ]
  },
  {
    "name": "Chupacabra > Head Butt",
    "input": "b+2,1+2",
    "hit_level": "h,h",
    "damage": "16,22",
    "startup": "i24~25",
    "block": "+2c",
    "hit": "+22d",
    "counter": "",
    "alternateInputs": [
      "b+2,1+2"
    ],
    "categories": [],
    "notes": [
      "Forces crouching on block.",
      "Move can be delayed by 10F",
      "Input can be delayed by 15F"
    ]
  },
  {
    "name": "Toll Kick",
    "input": "b+3",
    "hit_level": "h",
    "damage": "23",
    "startup": "i16~18",
    "block": "-10/-5",
    "hit": "+39d",
    "counter": "",
    "alternateInputs": [
      "b+3"
    ],
    "categories": [
      "powercrush"
    ],
    "notes": [
      "Tornado",
      "Balcony Break",
      "-5 on block after absorbing an attack in power crush state.",
      "9 chip damage on block after absorbing an attack in power crush state.",
      "10 chip damage on block after absorbing an attack in power crush state while in heat."
    ]
  },
  {
    "name": "Guillotine Drop",
    "input": "b+3:1+2",
    "hit_level": "h,t",
    "damage": "23,15",
    "startup": "i16~18",
    "block": "",
    "hit": "-7d",
    "counter": "",
    "alternateInputs": [
      "b+3:1+2"
    ],
    "categories": [
      "throw"
    ],
    "notes": [
      "Shifts to throw on front grounded hit.",
      "Input 1+2 before b+3 hits."
    ]
  },
  {
    "name": "Disgraceful Kick",
    "input": "b+4",
    "hit_level": "h",
    "damage": "25",
    "startup": "i17~21",
    "block": "+2",
    "hit": "+14gc",
    "counter": "",
    "alternateInputs": [
      "b+4"
    ],
    "categories": [],
    "notes": [
      "Balcony Break",
      "Shifts into BT stance.",
      "Forces crouching on hit"
    ]
  },
  {
    "name": "Capital Punishment",
    "input": "u+1+2",
    "hit_level": "m",
    "damage": "25",
    "startup": "i35~36",
    "block": "+2c",
    "hit": "+22d",
    "counter": "",
    "alternateInputs": [
      "u+1+2"
    ],
    "categories": [],
    "notes": [
      "Tap 1+2 otherwise it becomes u+1+2(hold).",
      "Forces Crouching on block."
    ]
  },
  {
    "name": "Burning Knuckle",
    "input": "u+1+2*",
    "hit_level": "m!",
    "damage": "40",
    "startup": "i67",
    "block": "",
    "hit": "+11d",
    "counter": "",
    "alternateInputs": [
      "u+1+2*"
    ],
    "categories": [],
    "notes": [
      "Unblockable mid.",
      "Auto switch side if fly over opponent."
    ]
  },
  {
    "name": "Water Parting Chop",
    "input": "uf+1",
    "hit_level": "h",
    "damage": "21",
    "startup": "i20~23",
    "block": "-3",
    "hit": "+36a(+27)",
    "counter": "",
    "alternateInputs": [
      "uf+1"
    ],
    "categories": [
      "homing"
    ],
    "notes": [
      "Homing",
      "Balcony Break"
    ]
  },
  {
    "name": "High Elbow Drop",
    "input": "uf+2",
    "hit_level": "m",
    "damage": "35",
    "startup": "i47~53",
    "block": "-17c",
    "hit": "-7d/-4c",
    "counter": "",
    "alternateInputs": [
      "uf+2"
    ],
    "categories": [],
    "notes": [
      "Hits OTG.",
      "u+2 to jump vertical (js9~), ub+2 to jump back (js9~).",
      "Force Crouching on block. (ub+2 also on hit)"
    ]
  },
  {
    "name": "Falling Heel Kick",
    "input": "uf+3",
    "hit_level": "m",
    "damage": "23",
    "startup": "i22~29",
    "block": "-10",
    "hit": "-1d",
    "counter": "",
    "alternateInputs": [
      "uf+3"
    ],
    "categories": [],
    "notes": [
      ""
    ]
  },
  {
    "name": "Jumping Knee Lift",
    "input": "uf+4",
    "hit_level": "m",
    "damage": "13",
    "startup": "i15",
    "block": "-13",
    "hit": "+33a(+23)",
    "counter": "",
    "alternateInputs": [
      "uf+4"
    ],
    "categories": [],
    "notes": [
      "Recovers 2F faster on hit or block (r30? t46?)",
      "Sometimes written Hopkick"
    ]
  },
  {
    "name": "Delayed Rising Toe Kick",
    "input": "uf,n,4",
    "hit_level": "m",
    "damage": "20",
    "startup": "i23~25",
    "block": "-13",
    "hit": "+32a(+22)",
    "counter": "",
    "alternateInputs": [
      "uf,n,4"
    ],
    "categories": [],
    "notes": [
      ""
    ]
  },
  {
    "name": "",
    "input": "ub+4",
    "hit_level": "m",
    "damage": "15",
    "startup": "i15",
    "block": "-13",
    "hit": "+19a(+9)",
    "counter": "+33a(+23)",
    "alternateInputs": [
      "ub+4"
    ],
    "categories": [],
    "notes": [
      "Jump straight up knee, very short range."
    ]
  },
  {
    "name": "Sole Crusher",
    "input": "uf+3+4",
    "hit_level": "m",
    "damage": "23",
    "startup": "i22~23",
    "block": "-12/-7",
    "hit": "+25g / +22g",
    "counter": "",
    "alternateInputs": [
      "uf+3+4"
    ],
    "categories": [
      "powercrush"
    ],
    "notes": [
      "Tornado",
      "-7 on block after absorbing an attack in power crush state.",
      "9 chip damage on block after absorbing an attack in power crush state.",
      "10 chip damage on block after absorbing an attack in power crush state while in heat.",
      "Shifts to r27 JGR on hit.",
      "Cancel shift into JGR on hit at +22 r55?  with input B"
    ]
  },
  {
    "name": "Stomache Smash / Jaguar Hammer",
    "input": "f,f,n,2",
    "hit_level": "L,(t)",
    "damage": "17,(30)",
    "startup": "i18",
    "block": "-13",
    "hit": "+5s/(0d)",
    "counter": "",
    "alternateInputs": [
      "f,f,n,2"
    ],
    "categories": [
      "throw"
    ],
    "notes": [
      "Shifts to throw on front grounded CH.",
      "Hits OTG."
    ]
  },
  {
    "name": "Lay Off",
    "input": "f,f,n,1+2",
    "hit_level": "m",
    "damage": "0",
    "startup": "i9",
    "block": "+0",
    "hit": "+7s",
    "counter": "+18s",
    "alternateInputs": [
      "f,f,n,1+2"
    ],
    "categories": [],
    "notes": [
      "Forces Standing on hit.",
      "Allows follow up on CH."
    ]
  },
  {
    "name": "Jaguar Hook",
    "input": "f,F,1",
    "hit_level": "m",
    "damage": "21",
    "startup": "i20~21",
    "block": "-5",
    "hit": "+14g",
    "counter": "+38d",
    "alternateInputs": [
      "f,F,1"
    ],
    "categories": [
      "homing"
    ],
    "notes": [
      "Homing",
      "Balcony Break"
    ]
  },
  {
    "name": "Beast Elbow",
    "input": "f,F,2",
    "hit_level": "m",
    "damage": "21",
    "startup": "i31~32",
    "block": "+7",
    "hit": "+12c",
    "counter": "",
    "alternateInputs": [
      "f,F,2"
    ],
    "categories": [],
    "notes": [
      "Forces crouching on hit.",
      "Allow crouching throw on hit.",
      "6 chip damage on block.",
      "8 chip damage on block in heat."
    ]
  },
  {
    "name": "Konvict Kick > DDT",
    "input": "f,F,4",
    "hit_level": "m",
    "damage": "25(30,14)",
    "startup": "i15",
    "block": "-15",
    "hit": "+14a(+4)",
    "counter": "+1d",
    "alternateInputs": [
      "f,F,4"
    ],
    "categories": [],
    "notes": [
      "Tornado",
      "Balcony Break",
      "Shifts to throw on front grounded CH."
    ]
  },
  {
    "name": "Exploder",
    "input": "f,F,3+4",
    "hit_level": "h",
    "damage": "25",
    "startup": "i28~30",
    "block": "0",
    "hit": "+24d(-34)",
    "counter": "",
    "alternateInputs": [
      "f,F,3+4"
    ],
    "categories": [],
    "notes": [
      "Wall Crush +2gc on block",
      "Balcony Break",
      "Chip damage on block. (extra near wall)",
      "Forces crouch on wall crush",
      "Recovers FUFT on whiff.",
      "7 chip damage on block.",
      "10 chip damage on block as wall crush.",
      "10 chip damage on block in heat.",
      "13 chip damage on block as wall crush in heat."
    ]
  },
  {
    "name": "Diving Body Press",
    "input": "f,F,2+3",
    "hit_level": "m,t",
    "damage": "20,15",
    "startup": "i21~43",
    "block": "-16c~+2c",
    "hit": "-19c~+3c/-5d",
    "counter": "",
    "alternateInputs": [
      "f,F,2+3"
    ],
    "categories": [
      "throw"
    ],
    "notes": [
      "Forces crouching on block and hit.",
      "Throw when hit standing in front close range."
    ]
  },
  {
    "name": "Strong Knee",
    "input": "f,f,F,3",
    "hit_level": "m",
    "damage": "25",
    "startup": "i20~25",
    "block": "+3",
    "hit": "+30(+22)",
    "counter": "",
    "alternateInputs": [
      "f,f,F,3"
    ],
    "categories": [],
    "notes": [
      "Balcony Break",
      "7 chip damage on block.",
      "10 chip damage on block in heat.",
      "Sometimes written wr3"
    ]
  },
  {
    "name": "Running Exploder",
    "input": "f,f,F,3+4",
    "hit_level": "m",
    "damage": "40",
    "startup": "i28~34",
    "block": "+17",
    "hit": "+32d(-26)",
    "counter": "",
    "alternateInputs": [
      "f,f,F,3+4"
    ],
    "categories": [],
    "notes": [
      "Balcony Break",
      "Sometimes written wr3+4"
    ]
  },
  {
    "name": "Leg Breaker",
    "input": "FC df+1",
    "hit_level": "L",
    "damage": "20",
    "startup": "i32~34",
    "block": "-12",
    "hit": "+73a(+57)",
    "counter": "",
    "alternateInputs": [
      "FC df+1"
    ],
    "categories": [],
    "notes": [
      "Can also be performed with f,n,d,DF+1/CD.1.",
      "Tornado on grounded hit."
    ]
  },
  {
    "name": "Body Blow",
    "input": "FC df+2",
    "hit_level": "m",
    "damage": "21",
    "startup": "i15",
    "block": "-14",
    "hit": "+56a",
    "counter": "",
    "alternateInputs": [
      "FC df+2"
    ],
    "categories": [],
    "notes": [
      "Crumple on hit."
    ]
  },
  {
    "name": "",
    "input": "FC d+3",
    "hit_level": "L",
    "damage": "10",
    "startup": "i18",
    "block": "-17",
    "hit": "-6",
    "counter": "",
    "alternateInputs": [
      "FC d+3"
    ],
    "categories": [],
    "notes": [
      "Can also be done by FC.db+3.",
      "Get extra range by FC.df+3/CD.DF+3."
    ]
  },
  {
    "name": "",
    "input": "ws1",
    "hit_level": "m",
    "damage": "12",
    "startup": "i10~11",
    "block": "-3",
    "hit": "+4s",
    "counter": "",
    "alternateInputs": [
      "ws1"
    ],
    "categories": [],
    "notes": [
      "Acts like 11 frame attack.",
      "Forces Standing on hit."
    ]
  },
  {
    "name": "",
    "input": "ws2",
    "hit_level": "m",
    "damage": "11",
    "startup": "i14",
    "block": "-9",
    "hit": "+1s",
    "counter": "",
    "alternateInputs": [
      "ws2"
    ],
    "categories": [
      "homing"
    ],
    "notes": [
      "Homing",
      "Forces Standing on hit."
    ]
  },
  {
    "name": "Round Trip Chop",
    "input": "ws2,2",
    "hit_level": "m,m",
    "damage": "11,25",
    "startup": "i15~16",
    "block": "-12",
    "hit": "+12g",
    "counter": "",
    "alternateInputs": [
      "ws2,2"
    ],
    "categories": [],
    "notes": [
      "Balcony Break",
      "Combo from 1st hit with 9F delay",
      "Combo from 1st CH with 16F delay",
      "Recover 3F faster on hit or block? (r30? t66?)",
      "Move can be delayed by 10F",
      "Input can be delayed by 16F"
    ]
  },
  {
    "name": "",
    "input": "ws3",
    "hit_level": "h",
    "damage": "20",
    "startup": "i16",
    "block": "0",
    "hit": "+22a(+12)",
    "counter": "",
    "alternateInputs": [
      "ws3"
    ],
    "categories": [],
    "notes": [
      ""
    ]
  },
  {
    "name": "Toe Smash",
    "input": "ws4",
    "hit_level": "m",
    "damage": "20",
    "startup": "i11~12",
    "block": "-6",
    "hit": "+5",
    "counter": "",
    "alternateInputs": [
      "ws4"
    ],
    "categories": [],
    "notes": [
      ""
    ]
  },
  {
    "name": "Snap Uppercut",
    "input": "ws1+2",
    "hit_level": "m",
    "damage": "20",
    "startup": "i18~19",
    "block": "-10",
    "hit": "+35a(+25)",
    "counter": "",
    "alternateInputs": [
      "ws1+2"
    ],
    "categories": [],
    "notes": [
      ""
    ]
  },
  {
    "name": "Beast Step",
    "input": "f,n,d,df",
    "hit_level": "",
    "damage": "",
    "startup": "",
    "block": "",
    "hit": "",
    "counter": "",
    "alternateInputs": [
      "f,n,d,df"
    ],
    "categories": [],
    "notes": [
      "Duck high while moving forward.",
      "Input f,n,d,df,f+(button) for instant ws moves.",
      "1st f cannot be held more than 10 frames."
    ]
  },
  {
    "name": "Knee Lift",
    "input": "CD DF+4",
    "hit_level": "m",
    "damage": "21",
    "startup": "i15~16",
    "block": "-9",
    "hit": "+49a(+18)",
    "counter": "+53a",
    "alternateInputs": [
      "CD DF+4"
    ],
    "categories": [],
    "notes": [
      "Special down state that allows low juggle (on normal hit).",
      "Crumple on CH for full combo."
    ]
  },
  {
    "name": "Black Bomb",
    "input": "CD 1+2",
    "hit_level": "M",
    "damage": "24",
    "startup": "i20~23",
    "block": "-5c",
    "hit": "+16d",
    "counter": "+52a",
    "alternateInputs": [
      "CD 1+2"
    ],
    "categories": [],
    "notes": [
      "Balcony Break",
      "Bounce off ground on CH for full combo."
    ]
  },
  {
    "name": "Blind Kick",
    "input": "BT 3",
    "hit_level": "m",
    "damage": "18",
    "startup": "i13~14",
    "block": "-13",
    "hit": "+9s",
    "counter": "+50d",
    "alternateInputs": [
      "BT 3"
    ],
    "categories": [],
    "notes": [
      "Tornado",
      "Hits OTG. Forces standing on normal hit.",
      "Crumple on CH for full combo."
    ]
  },
  {
    "name": "Blind Kick > Neck Breaker",
    "input": "BT 3:1+2",
    "hit_level": "m,t",
    "damage": "18,20",
    "startup": "i13~14",
    "block": "",
    "hit": "+0d",
    "counter": "",
    "alternateInputs": [
      "BT 3:1+2"
    ],
    "categories": [
      "throw"
    ],
    "notes": [
      "Floor Break",
      "Throw when hit standing in front close range.",
      "Just frame input."
    ]
  },
  {
    "name": "Atomic Blaster",
    "input": "BT 1+2",
    "hit_level": "h!",
    "damage": "45",
    "startup": "i26~30",
    "block": "",
    "hit": "+2d",
    "counter": "",
    "alternateInputs": [
      "BT 1+2"
    ],
    "categories": [],
    "notes": [
      "Unblockable high attack."
    ]
  },
  {
    "name": "Moonsault Body Press",
    "input": "BT 1+4",
    "hit_level": "m!",
    "damage": "30",
    "startup": "i41~47",
    "block": "",
    "hit": "+6d",
    "counter": "",
    "alternateInputs": [
      "BT 1+4"
    ],
    "categories": [],
    "notes": [
      "Unblockable mid attack."
    ]
  },
  {
    "name": "Low Drop Kick (BT)",
    "input": "BT d+4",
    "hit_level": "l",
    "damage": "20",
    "startup": "i22~24",
    "block": "-14",
    "hit": "-2d",
    "counter": "+28d",
    "alternateInputs": [
      "BT d+4"
    ],
    "categories": [],
    "notes": [
      "Recovers in FDFT on block and whiff.",
      "Also can be done in backturn crouching."
    ]
  },
  {
    "name": "Jaguar Step (BT)",
    "input": "BT 3+4",
    "hit_level": "",
    "damage": "",
    "startup": "",
    "block": "",
    "hit": "",
    "counter": "",
    "alternateInputs": [
      "BT 3+4"
    ],
    "categories": [],
    "notes": [
      "Jaguar Step away from the oppponent while keeping backturn stance on recovery.",
      "Can cancel into BT.1+2 / BT.1+4 unblockable.",
      "Can hold 3+4 to keep spinning.",
      "Cannot Reverse Jaguar Step in BT stance."
    ]
  },
  {
    "name": "Jaguar Step",
    "input": "3+4",
    "hit_level": "",
    "damage": "",
    "startup": "",
    "block": "",
    "hit": "",
    "counter": "",
    "alternateInputs": [
      "3+4"
    ],
    "categories": [],
    "notes": [
      "Hold to continue spinning and power up strikes, but King doesn't change direction.",
      "King gets dizzy and falls after 6th spin."
    ]
  },
  {
    "name": "Backwards Jaguar Step",
    "input": "b+3+4",
    "hit_level": "",
    "damage": "",
    "startup": "",
    "block": "",
    "hit": "",
    "counter": "",
    "alternateInputs": [
      "b+3+4"
    ],
    "categories": [],
    "notes": [
      "Cannot be held to continue spinning."
    ]
  },
  {
    "name": "Jaguar Step > Hook",
    "input": "JGS 1",
    "hit_level": "h",
    "damage": "21/25/31",
    "startup": "i17~18/i19~20",
    "block": "-7/-1",
    "hit": "+47d/+53d",
    "counter": "",
    "alternateInputs": [
      "JGS 1"
    ],
    "categories": [],
    "notes": [
      "Crumple on hit.",
      "On block / hit / startup increases up to 2nd spin.",
      "Damage increase up to 3rd spin."
    ]
  },
  {
    "name": "Jaguar Step > Hammer",
    "input": "JGS 2",
    "hit_level": "m",
    "damage": "15/18/22",
    "startup": "i11~12",
    "block": "-9/-2/0c",
    "hit": "+12c",
    "counter": "",
    "alternateInputs": [
      "JGS 2"
    ],
    "categories": [],
    "notes": [
      "Forces Crouching on hit.",
      "Forces Crouching on block from 3rd spin on.",
      "Damage increase up to 3rd spin."
    ]
  },
  {
    "name": "Jaguar Step > Sobat",
    "input": "JGS 3",
    "hit_level": "m",
    "damage": "23/27/34",
    "startup": "i22~23",
    "block": "-5/-1",
    "hit": "+21a(+12)/+25a(+16)",
    "counter": "",
    "alternateInputs": [
      "JGS 3"
    ],
    "categories": [],
    "notes": [
      "Balcony Break",
      "On block / hit increases up to 2nd spin.",
      "Damage increase up to 3rd spin."
    ]
  },
  {
    "name": "Jaguar Step > Sobat & Press",
    "input": "JGS 3,2+3",
    "hit_level": "m,m,t",
    "damage": "23/27/34,20,15",
    "startup": "i21~43",
    "block": "-16c~+2c",
    "hit": "-19c~+3c/-5d",
    "counter": "",
    "alternateInputs": [
      "JGS 3,2+3"
    ],
    "categories": [
      "throw"
    ],
    "notes": [
      "Throw when hit standing in front close range.",
      "Doesn't combo from JGS.3, but trades with 10 frame jab.",
      "Properties not changed with extra spins."
    ]
  },
  {
    "name": "Jaguar Step > High Kick",
    "input": "JGS 4",
    "hit_level": "h",
    "damage": "40/42/52",
    "startup": "i17~18",
    "block": "+8/+15",
    "hit": "+5a(-4)/+10a(+1)",
    "counter": "",
    "alternateInputs": [
      "JGS 4"
    ],
    "categories": [],
    "notes": [
      "Balcony Break",
      "Guard Break",
      "Chip damage on block.",
      "On block / hit increases up to 2nd spin.",
      "Damage increase up to 3rd spin."
    ]
  },
  {
    "name": "Jaguar Step > Mid Kick",
    "input": "JGS df+4",
    "hit_level": "m",
    "damage": "30/36/45",
    "startup": "i17~19",
    "block": "-16/+8",
    "hit": "+5a(-4)",
    "counter": "",
    "alternateInputs": [
      "JGS df+4"
    ],
    "categories": [],
    "notes": [
      "Balcony Break",
      "On block increases up to 2nd spin.",
      "Damage increase up to 3rd spin."
    ]
  },
  {
    "name": "Jaguar Sprint",
    "input": "f+3+4",
    "hit_level": "",
    "damage": "",
    "startup": "",
    "block": "",
    "hit": "",
    "counter": "",
    "alternateInputs": [
      "f+3+4"
    ],
    "categories": [],
    "notes": [
      "Cancel to r25 with b on frame 34~ at the earliest, able to block high.",
      "Gains armor during Heat.",
      "Partially uses remaining Heat time (same for uf+3+4 / db+1+2,3+4 / b+1+2 )."
    ]
  },
  {
    "name": "Running Elbow Smash",
    "input": "JGR 1",
    "hit_level": "m",
    "damage": "21",
    "startup": "i16~17",
    "block": "-8",
    "hit": "+39d/+75a(+59)",
    "counter": "",
    "alternateInputs": [
      "JGR 1"
    ],
    "categories": [],
    "notes": [
      "In heat it becomes Tornado on grounded hit.",
      "Partially uses remaining Heat time."
    ]
  },
  {
    "name": "Jaguar Axe",
    "input": "JGR 2",
    "hit_level": "h",
    "damage": "26",
    "startup": "i18~19",
    "block": "+3/+6/+18c",
    "hit": "+4d",
    "counter": "",
    "alternateInputs": [
      "JGR 2"
    ],
    "categories": [],
    "notes": [
      "Chip damage on block.",
      "In heat it becomes +6 on block, and forces crouching +18 near wall.",
      "Partially uses remaining Heat time."
    ]
  },
  {
    "name": "Sprint K.",
    "input": "JGR 3",
    "hit_level": "m",
    "damage": "30",
    "startup": "i22~23",
    "block": "-9",
    "hit": "+11d (+1)",
    "counter": "",
    "alternateInputs": [
      "JGR 3"
    ],
    "categories": [
      "homing"
    ],
    "notes": [
      "Balcony Break",
      "Homing"
    ]
  },
  {
    "name": "Dashing Low Drop Kick",
    "input": "JGR 4",
    "hit_level": "L",
    "damage": "20",
    "startup": "i20~24",
    "block": "-21",
    "hit": "+0c",
    "counter": "",
    "alternateInputs": [
      "JGR 4"
    ],
    "categories": [],
    "notes": [
      ""
    ]
  },
  {
    "name": "Diving Body Press",
    "input": "JGR 2+3",
    "hit_level": "M,t",
    "damage": "20,15",
    "startup": "i21~43",
    "block": "-16c~+2c",
    "hit": "-19c~+3c/-5d",
    "counter": "",
    "alternateInputs": [
      "JGR 2+3"
    ],
    "categories": [
      "throw"
    ],
    "notes": [
      "Throw when hit standing in front close range.",
      "King recovers off axis"
    ]
  },
  {
    "name": "Anger Of The Beast (Rage Art)",
    "input": "in rage df+1+2",
    "hit_level": "m,t",
    "damage": "55+",
    "startup": "i20",
    "block": "-15",
    "hit": "+0d",
    "counter": "",
    "alternateInputs": [
      "in rage df+1+2"
    ],
    "categories": [],
    "notes": [
      "Rage Art",
      "Removes Recoverable Health",
      "Reversal Break",
      "Damage increases with lower health, maximum 82",
      "Freezes match timer on activation and on hit",
      "Restores recoverable health on hit",
      "Transition to attack throw on hit",
      "Consumes Rage"
    ]
  },
  {
    "name": "Ki Charge",
    "input": "1+2+3+4",
    "hit_level": "",
    "damage": "",
    "startup": "",
    "block": "",
    "hit": "",
    "counter": "",
    "alternateInputs": [
      "1+2+3+4"
    ],
    "categories": [],
    "notes": [
      "Takes some time to charge and can cancel into anything.",
      "After charged next hit by either side becomes counter hit."
    ]
  },
  {
    "name": "Wall Jumping Attack",
    "input": "WallBack b,b,ub",
    "hit_level": "t / m",
    "damage": "45 / 21",
    "startup": "i43~48 / i44~63",
    "block": "-8",
    "hit": "+2 / +15",
    "counter": "",
    "alternateInputs": [
      "WallBack b,b,ub"
    ],
    "categories": [
      "throw"
    ],
    "notes": [
      "Airborne from 5F, invincibility from 8 to 13F.",
      "Unbreakable throw near wall, becomes air attack if throw not connected.",
      "Side switch. Opponent recovers in FUFA."
    ]
  },
  {
    "name": "Low Parry",
    "input": "DF",
    "hit_level": "r(l)",
    "damage": "0",
    "startup": "i43~48 / i44~63",
    "block": "",
    "hit": "+51a(+35)",
    "counter": "",
    "alternateInputs": [
      "DF"
    ],
    "categories": [
      "parry"
    ],
    "notes": [
      "Generic low parry.",
      "Tornado affect on success."
    ]
  },
  {
    "name": "Arm Whip",
    "input": "b+1+3",
    "hit_level": "r(m)",
    "damage": "25",
    "startup": "i10",
    "block": "",
    "hit": "+2d",
    "counter": "",
    "alternateInputs": [
      "b+1+3"
    ],
    "categories": [
      "parry"
    ],
    "notes": [
      "Floor Break",
      "Parry opponent's right punch.",
      "Side Switch. Opponent recovers in FUFR."
    ]
  },
  {
    "name": "Spinning Heel Hold",
    "input": "b+2+4",
    "hit_level": "r(m)",
    "damage": "25",
    "startup": "i10",
    "block": "",
    "hit": "+24d",
    "counter": "",
    "alternateInputs": [
      "b+2+4"
    ],
    "categories": [
      "parry"
    ],
    "notes": [
      "Parry opponent's left kick.",
      "Side Switch. Opponent recovers in FUFL."
    ]
  },
  {
    "name": "Leg Screw > Figure Four Leg Lock",
    "input": "b+2+4:3+4",
    "hit_level": "r(m)",
    "damage": "25(,28)",
    "startup": "i10",
    "block": "",
    "hit": "+27d(+1d)",
    "counter": "",
    "alternateInputs": [
      "b+2+4:3+4"
    ],
    "categories": [
      "parry"
    ],
    "notes": [
      "2 Throw Break",
      "Parry opponent's right kick.",
      "Just frame input right before camera returns to normal position to deal extra damage.",
      "Opponent recovers in FUFT."
    ]
  },
  {
    "name": "Victory Palm",
    "input": "ss2",
    "hit_level": "h",
    "damage": "25",
    "startup": "i19~20",
    "block": "-5",
    "hit": "+18a(+9)",
    "counter": "",
    "alternateInputs": [
      "ss2"
    ],
    "categories": [],
    "notes": [
      "Balcony Break"
    ]
  },
  {
    "name": "Side Step to RSSB2 / RSSB1",
    "input": "ss2+4",
    "hit_level": "t",
    "damage": "15 / 20",
    "startup": "i13",
    "block": "-3",
    "hit": "+0d / +1d",
    "counter": "",
    "alternateInputs": [
      "ss2+4"
    ],
    "categories": [
      "throw",
      "homing"
    ],
    "notes": [
      "Homing",
      "2 throw break (except from behind).",
      "RSSB2 from side/behind, RSSB1 from front, doesn't change to left/right/behind throw.",
      "Opponent recovers in FUFT.",
      "Throw can be canceled by input b/db."
    ]
  },
  {
    "name": "Reverse Special Stretch Bomb (Cancel)",
    "input": "ss2+4,b/db",
    "hit_level": "",
    "damage": "",
    "startup": "",
    "block": "",
    "hit": "",
    "counter": "",
    "alternateInputs": [
      "ss2+4,b/db"
    ],
    "categories": [],
    "notes": [
      "Side Step that ducks high and covers long distance quickly, recovers in crouch.",
      "Input by u/d,n,n+2+4,b/db."
    ]
  },
  {
    "name": "Deadly Boomerang",
    "input": "ss3+4",
    "hit_level": "h",
    "damage": "50",
    "startup": "i27~31",
    "block": "0",
    "hit": "+0d",
    "counter": "",
    "alternateInputs": [
      "ss3+4"
    ],
    "categories": [],
    "notes": [
      "Deals a lot of chip damage on block.",
      "Tracks side steps.",
      "In game frame data incorrectly shows that SSL 3+4 is i21"
    ]
  },
  {
    "name": "Whirling Spring Kick",
    "input": "FUFT b+3+4",
    "hit_level": "m",
    "damage": "25",
    "startup": "i16~28",
    "block": "-25",
    "hit": "+4a(-6)",
    "counter": "",
    "alternateInputs": [
      "FUFT b+3+4"
    ],
    "categories": [],
    "notes": [
      "Balcony Break",
      "Faster than normal spring kick and knocks down."
    ]
  },
  {
    "name": "Winding Nut",
    "input": "1+3 / f+1+3",
    "hit_level": "t",
    "damage": "35",
    "startup": "i12~15 / i15~17",
    "block": "-6",
    "hit": "+0d",
    "counter": "",
    "alternateInputs": [
      "1+3 / f+1+3"
    ],
    "categories": [
      "throw",
      "homing"
    ],
    "notes": [
      "Homing",
      "1 or 2 throw break.",
      "Input f+1+3 to increase throw range, but its startup is 3 frames slower.",
      "Opponent recovers in FUFA.",
      "Side switch on successful throw break"
    ]
  },
  {
    "name": "Suplex",
    "input": "2+4 / f+2+4",
    "hit_level": "t",
    "damage": "35",
    "startup": "i12~15 / i15~17",
    "block": "-3",
    "hit": "+0d",
    "counter": "",
    "alternateInputs": [
      "2+4 / f+2+4"
    ],
    "categories": [
      "throw",
      "homing"
    ],
    "notes": [
      "Homing",
      "1 or 2 throw break.",
      "Input f+2+4 to increase throw range, but its startup is 3 frames slower.",
      "Side switch. Opponent recovers in FUFA."
    ]
  },
  {
    "name": "Executioner Drop",
    "input": "uf+1+2 / uf+1+2,B",
    "hit_level": "t",
    "damage": "30",
    "startup": "i12",
    "block": "-6",
    "hit": "+19d(-7) / +17d(-13)",
    "counter": "",
    "alternateInputs": [
      "uf+1+2 / uf+1+2,B"
    ],
    "categories": [
      "throw"
    ],
    "notes": [
      "1+2 throw break.",
      "Hold b to throw backwards.",
      "Damage becomes 15 on wall splat.",
      "Opponent recovers in FUFT."
    ]
  },
  {
    "name": "Argentina Backbreaker",
    "input": "(Left side throw)",
    "hit_level": "t",
    "damage": "40",
    "startup": "(depends)",
    "block": "-3",
    "hit": "+36d",
    "counter": "",
    "alternateInputs": [
      "(Left side throw)"
    ],
    "categories": [
      "throw"
    ],
    "notes": [
      "1 throw break.",
      "Any throw on standing opponent's left side.",
      "Side switch. Opponent recovers in FUFR."
    ]
  },
  {
    "name": "Knee Crusher",
    "input": "(Right side throw)",
    "hit_level": "t",
    "damage": "42",
    "startup": "(depends)",
    "block": "-3",
    "hit": "+21d",
    "counter": "",
    "alternateInputs": [
      "(Right side throw)"
    ],
    "categories": [
      "throw"
    ],
    "notes": [
      "2 throw break.",
      "Any throw on standing opponent's right side.",
      "Opponent recovers in FUFT."
    ]
  },
  {
    "name": "Half Boston Crab",
    "input": "(Behind 1 throw)",
    "hit_level": "t",
    "damage": "60",
    "startup": "(depends)",
    "block": "",
    "hit": "+0d",
    "counter": "",
    "alternateInputs": [
      "(Behind 1 throw)"
    ],
    "categories": [
      "throw"
    ],
    "notes": [
      "Cannot throw break.",
      "Any 1/1+2 break throw behind opponent's back, as well as RKO and chain throws.",
      "Side switch. Opponent recovers in FDFL."
    ]
  },
  {
    "name": "Cobra Twist",
    "input": "(Behind 2 throw)",
    "hit_level": "t",
    "damage": "60",
    "startup": "(depends)",
    "block": "",
    "hit": "-1d",
    "counter": "",
    "alternateInputs": [
      "(Behind 2 throw)"
    ],
    "categories": [
      "throw"
    ],
    "notes": [
      "Cannot throw break.",
      "Any 2 break throw behind opponent's back except chain throws.",
      "Side switch? Opponent recovers in FDFL."
    ]
  },
  {
    "name": "Knee Bash",
    "input": "df+2+3",
    "hit_level": "t",
    "damage": "40",
    "startup": "i12",
    "block": "-2",
    "hit": "+0d",
    "counter": "",
    "alternateInputs": [
      "df+2+3"
    ],
    "categories": [
      "throw"
    ],
    "notes": [
      "2 throw break.",
      "Opponent recovers in FUFT."
    ]
  },
  {
    "name": "Figure Four Leg Lock",
    "input": "db+2+3",
    "hit_level": "t",
    "damage": "40 (8+20+12)",
    "startup": "i12",
    "block": "-6",
    "hit": "+1d / 0d",
    "counter": "",
    "alternateInputs": [
      "db+2+3"
    ],
    "categories": [
      "throw"
    ],
    "notes": [
      "1+2 throw break.",
      "Just frame input 3+4 when the last hit connects (frame 207 of throw), reverse 26 damage back to King.",
      "Opponent recovers in FUFT / FDFT."
    ]
  },
  {
    "name": "Throw Away",
    "input": "b+1+2(,f,F)",
    "hit_level": "t",
    "damage": "0",
    "startup": "i12~17",
    "block": "-3",
    "hit": "+14g / -2",
    "counter": "",
    "alternateInputs": [
      "b+1+2(,f,F)"
    ],
    "categories": [
      "throw",
      "homing"
    ],
    "notes": [
      "Homing",
      "1+2 throw break. Side switch.",
      "Damage becomes 15 on wall splat.",
      "Shifts to JGR, input f,F / b,B to cancel shift."
    ]
  },
  {
    "name": "Throw away > Back Swing",
    "input": "b+1+2,1+2(,f,F)",
    "hit_level": "t",
    "damage": "0",
    "startup": "i12~17",
    "block": "",
    "hit": "+11g / -6",
    "counter": "",
    "alternateInputs": [
      "b+1+2,1+2(,f,F)"
    ],
    "categories": [
      "throw"
    ],
    "notes": [
      "1+2 throw break.",
      "Damage becomes 15 on wall splat.",
      "Shifts to JGR, input f,F / b,B to cancel shift."
    ]
  },
  {
    "name": "Tombstone Pile Driver",
    "input": "db,n,f+2+4",
    "hit_level": "t",
    "damage": "53",
    "startup": "i11",
    "block": "-2",
    "hit": "-1d",
    "counter": "",
    "alternateInputs": [
      "db,n,f+2+4"
    ],
    "categories": [
      "throw"
    ],
    "notes": [
      "Floor Break",
      "2 throw break. Can also be done by qcb,n,f+2+4 / b,db,d,n,f+2+4.",
      "Opponent recovers in FUFA."
    ]
  },
  {
    "name": "Muscle Buster",
    "input": "qcb+1+2",
    "hit_level": "t",
    "damage": "50",
    "startup": "i11",
    "block": "-6",
    "hit": "-6d",
    "counter": "",
    "alternateInputs": [
      "qcb+1+2"
    ],
    "categories": [
      "throw"
    ],
    "notes": [
      "Floor Break",
      "1+2 throw break. Side switch.",
      "King recovers in backturn stance.",
      "Partially restores remaining Heat time.",
      "Opponent recovers in FUFA."
    ]
  },
  {
    "name": "Tomahawk",
    "input": "f,f,F+2+4",
    "hit_level": "t",
    "damage": "40(45)",
    "startup": "i10",
    "block": "-5",
    "hit": "+1d",
    "counter": "",
    "alternateInputs": [
      "f,f,F+2+4"
    ],
    "categories": [
      "throw"
    ],
    "notes": [
      "1+2 throw break.",
      "Input quickly to \"blue spark\" (+5 damage).",
      "Partially restores remaining Heat time.",
      "Opponent recovers in FUFL.",
      "Sometimes written Shining Wizard"
    ]
  },
  {
    "name": "Giant Swing",
    "input": "f,hcf+1",
    "hit_level": "t",
    "damage": "45(50),20 / 70",
    "startup": "i10",
    "block": "-13",
    "hit": "-22d(-50)",
    "counter": "",
    "alternateInputs": [
      "f,hcf+1"
    ],
    "categories": [
      "throw"
    ],
    "notes": [
      "1 throw break. Side switch.",
      "Input quickly to \"blue spark\" (+5 damage).",
      "Partially restores remaining Heat time.",
      "Mash 1/2/3/4 to roll in midscreen to reduce 20 damage, on wall splat damage is 70.",
      "Opponent recovers in FUFT if fails to roll.",
      "Sometimes written GS"
    ]
  },
  {
    "name": "Tijuana Twister",
    "input": "f,hcf+2",
    "hit_level": "t",
    "damage": "50(55)",
    "startup": "i12~14",
    "block": "-6",
    "hit": "+1d",
    "counter": "",
    "alternateInputs": [
      "f,hcf+2"
    ],
    "categories": [
      "throw"
    ],
    "notes": [
      "2 throw break.",
      "Input quickly to \"blue spark\" (+5 damage).",
      "Partially restores remaining Heat time.",
      "f,b,d,f are required, so it can be done by f,b,db,d(,n),f+2. (same for Giant Swing)",
      "Opponent recovers in FUFL.",
      "Sometimes written TT"
    ]
  },
  {
    "name": "Pile Driver (PD)",
    "input": "qcf+1",
    "hit_level": "t",
    "damage": "30",
    "startup": "i11",
    "block": "-2/-7",
    "hit": "+8d",
    "counter": "",
    "alternateInputs": [
      "qcf+1"
    ],
    "categories": [
      "throw"
    ],
    "notes": [
      "1 throw break.",
      "Opponent recovers in FUFT."
    ]
  },
  {
    "name": "Double Arm Face Buster (from PD)",
    "input": "PD 1+2,1+2",
    "hit_level": "t",
    "damage": "35",
    "startup": "i11",
    "block": "-7",
    "hit": "-14d",
    "counter": "",
    "alternateInputs": [
      "PD 1+2,1+2"
    ],
    "categories": [
      "throw"
    ],
    "notes": [
      "Floor Break",
      "2 throw break. (when legs lifted to the top)",
      "Opponent recovers in FDFA."
    ]
  },
  {
    "name": "Boston Crab (from PD)",
    "input": "PD 1+2,3,4,1+2",
    "hit_level": "t",
    "damage": "45",
    "startup": "i11",
    "block": "-7",
    "hit": "+0d",
    "counter": "",
    "alternateInputs": [
      "PD 1+2,3,4,1+2"
    ],
    "categories": [
      "throw"
    ],
    "notes": [
      "1+2 throw break. (when legs lifted to the top)",
      "Could use ki charge button for 1+2 input.",
      "Opponent recovers in FDFL."
    ]
  },
  {
    "name": "Clothesline Press (Rock Bottom)",
    "input": "FC db,d,db+1+2",
    "hit_level": "t",
    "damage": "45",
    "startup": "i12",
    "block": "-6",
    "hit": "+0d",
    "counter": "",
    "alternateInputs": [
      "FC db,d,db+1+2"
    ],
    "categories": [
      "throw"
    ],
    "notes": [
      "Floor Break",
      "1+2 throw break.",
      "Opponent recovers in FUFR."
    ]
  },
  {
    "name": "Stretch Buster",
    "input": "Behind b,f+1+2",
    "hit_level": "t",
    "damage": "75",
    "startup": "i10",
    "block": "",
    "hit": "+1d",
    "counter": "",
    "alternateInputs": [
      "Behind b,f+1+2"
    ],
    "categories": [
      "throw"
    ],
    "notes": [
      "Floor Break",
      "Cannot throw break.",
      "Opponent recovers FUFR."
    ]
  },
  {
    "name": "Ultimate Tackle (UT)",
    "input": "FC 1+2",
    "hit_level": "t(s)",
    "damage": "0",
    "startup": "i26",
    "block": "-5",
    "hit": "+3d",
    "counter": "",
    "alternateInputs": [
      "FC 1+2"
    ],
    "categories": [
      "throw"
    ],
    "notes": [
      "1+2 throw break (except from behind).",
      "Catches standing and crouching opponent from all directions."
    ]
  },
  {
    "name": "Ultimate Punch",
    "input": "UT,2,1,2,1",
    "hit_level": "t",
    "damage": "5,5,5,15",
    "startup": "i26",
    "block": "+0",
    "hit": "+0d",
    "counter": "",
    "alternateInputs": [
      "UT,2,1,2,1"
    ],
    "categories": [
      "throw"
    ],
    "notes": [
      "Could be any 1/2 combination (e.g. 1,1,1,1 / 1,2,2,1)",
      "Throw break the 1st/4th hit by input the opposite to King's 1st/4th button."
    ]
  },
  {
    "name": "Armbar",
    "input": "UT,1+2",
    "hit_level": "t",
    "damage": "25",
    "startup": "i26",
    "block": "-9",
    "hit": "+1d",
    "counter": "",
    "alternateInputs": [
      "UT,1+2"
    ],
    "categories": [
      "throw"
    ],
    "notes": [
      "1+2 throw break.",
      "Can also input at 3rd hit of Ultimate Punch.",
      "Opponent recovers in FUFR."
    ]
  },
  {
    "name": "Arm Twist",
    "input": "UT,1+2,1+2",
    "hit_level": "t,t",
    "damage": "25,10",
    "startup": "i26",
    "block": "",
    "hit": "+1d",
    "counter": "",
    "alternateInputs": [
      "UT,1+2,1+2"
    ],
    "categories": [
      "throw"
    ],
    "notes": [
      "Cannot throw break.",
      "Opponent recovers in FUFA."
    ]
  },
  {
    "name": "Leg Cross Hold",
    "input": "UT,3+4",
    "hit_level": "t",
    "damage": "20",
    "startup": "i69?",
    "block": "+0",
    "hit": "+1d",
    "counter": "",
    "alternateInputs": [
      "UT,3+4"
    ],
    "categories": [
      "throw"
    ],
    "notes": [
      "3+4 throw break.",
      "Throw break window: input or hold 3+4 during frames 20-60",
      "Can also input at 3rd hit of Ultimate Punch.",
      "Opponent recovers in FUFR."
    ]
  },
  {
    "name": "Stretch Combo",
    "input": "UT,3+4:1+2",
    "hit_level": "t,t",
    "damage": "20,30",
    "startup": "i69?",
    "block": "",
    "hit": "+1d",
    "counter": "",
    "alternateInputs": [
      "UT,3+4:1+2"
    ],
    "categories": [
      "throw"
    ],
    "notes": [
      "Input 1+2 during frames 68-70 of Leg Cross Hold",
      "Cannot throw break.",
      "Opponent recovers in FDFL."
    ]
  },
  {
    "name": "Iron Lariat",
    "input": "d+1+3",
    "hit_level": "t(c)",
    "damage": "35",
    "startup": "i12~13",
    "block": "",
    "hit": "+0d",
    "counter": "",
    "alternateInputs": [
      "d+1+3"
    ],
    "categories": [
      "throw"
    ],
    "notes": [
      "Floor Break",
      "Crouch throw, cannot throw break.",
      "Can also be done by db+1+3 and in FC too.",
      "Opponent recovers in FDFA."
    ]
  },
  {
    "name": "V Driver",
    "input": "d+2+4",
    "hit_level": "t(c)",
    "damage": "35",
    "startup": "i12~13",
    "block": "",
    "hit": "+0d",
    "counter": "",
    "alternateInputs": [
      "d+2+4"
    ],
    "categories": [
      "throw"
    ],
    "notes": [
      "Floor Break",
      "Crouch throw, cannot throw break.",
      "Can also be done by db+2+4 and in FC too.",
      "Opponent recovers in FUFA."
    ]
  },
  {
    "name": "Swing Away",
    "input": "FUFT db+1+3_2+4",
    "hit_level": "t(g)",
    "damage": "20,10 / 35",
    "startup": "i18~20",
    "block": "+0",
    "hit": "+1d(-40)",
    "counter": "",
    "alternateInputs": [
      "FUFT db+1+3_2+4"
    ],
    "categories": [
      "throw"
    ],
    "notes": [
      "1 or 2 throw break, depending on King's input.",
      "Mash 1/2/3/4 to roll in midscreen to reduce 10 damage, on wall splat damage is 35.",
      "Opponent recovers in FUFT if fails to roll."
    ]
  },
  {
    "name": "Head Bomber",
    "input": "FUFT DB+1+3",
    "hit_level": "t(g)",
    "damage": "25",
    "startup": "i18~20",
    "block": "+0",
    "hit": "+0d",
    "counter": "",
    "alternateInputs": [
      "FUFT DB+1+3"
    ],
    "categories": [
      "throw"
    ],
    "notes": [
      "Floor Break",
      "1 throw break.",
      "Opponent recovers in FUFT."
    ]
  },
  {
    "name": "Figure Four Leg Lock (OTG)",
    "input": "FUFT DB+2+4",
    "hit_level": "t(g)",
    "damage": "28",
    "startup": "i18~20",
    "block": "+0",
    "hit": "+1d",
    "counter": "",
    "alternateInputs": [
      "FUFT DB+2+4"
    ],
    "categories": [
      "throw"
    ],
    "notes": [
      "2 throw break.",
      "Opponent recovers in FUFT."
    ]
  },
  {
    "name": "Half Boston Crab (OTG)",
    "input": "FDFT db+1+3_2+4",
    "hit_level": "t(g)",
    "damage": "30",
    "startup": "i18~20",
    "block": "+0",
    "hit": "+22d",
    "counter": "",
    "alternateInputs": [
      "FDFT db+1+3_2+4"
    ],
    "categories": [
      "throw"
    ],
    "notes": [
      "1 or 2 throw break, depending on King's input.",
      "Side Switch.",
      "Opponent recovers in FDFL."
    ]
  },
  {
    "name": "Shoulder Cracker",
    "input": "FUFA db+1+3_2+4",
    "hit_level": "t(g)",
    "damage": "28",
    "startup": "i18~20",
    "block": "+0",
    "hit": "+0d",
    "counter": "",
    "alternateInputs": [
      "FUFA db+1+3_2+4"
    ],
    "categories": [
      "throw"
    ],
    "notes": [
      "1 or 2 throw break, depending on King's input.",
      "Opponent recovers in FUFR."
    ]
  },
  {
    "name": "Wing Tearer",
    "input": "FDFA db+1+3_2+4",
    "hit_level": "t(g)",
    "damage": "32",
    "startup": "i18~20",
    "block": "+0",
    "hit": "+0d",
    "counter": "",
    "alternateInputs": [
      "FDFA db+1+3_2+4"
    ],
    "categories": [
      "throw"
    ],
    "notes": [
      "1 or 2 throw break, depending on King's input.",
      "Opponent recovers in FDFA."
    ]
  },
  {
    "name": "Turn Over",
    "input": "FUFL db+1+3_2+4/ FUFin rage db+1+3_2+4",
    "hit_level": "t(g)",
    "damage": "0",
    "startup": "i18~20",
    "block": "+0",
    "hit": "+25d",
    "counter": "",
    "alternateInputs": [
      "FUFL db+1+3_2+4/ FUFin rage db+1+3_2+4"
    ],
    "categories": [
      "throw"
    ],
    "notes": [
      "1 or 2 throw break, depending on King's input.",
      "Opponent recovers in FDFL/FDFR."
    ]
  },
  {
    "name": "Camel Clutch",
    "input": "FDFin rage db+1+3_2+4",
    "hit_level": "t(g)",
    "damage": "35",
    "startup": "i18~20",
    "block": "+0",
    "hit": "+0d",
    "counter": "",
    "alternateInputs": [
      "FDFin rage db+1+3_2+4"
    ],
    "categories": [
      "throw"
    ],
    "notes": [
      "1 or 2 throw break, depending on King's input.",
      "Side Switch.",
      "Opponent recovers in FDFL."
    ]
  },
  {
    "name": "Bow & Arrow Stretch Hold",
    "input": "FDFL db+1+3_2+4",
    "hit_level": "t(g)",
    "damage": "37",
    "startup": "i18~20",
    "block": "+0",
    "hit": "+0d",
    "counter": "",
    "alternateInputs": [
      "FDFL db+1+3_2+4"
    ],
    "categories": [
      "throw"
    ],
    "notes": [
      "1 or 2 throw break, depending on King's input.",
      "Opponent recovers in FDFL."
    ]
  },
  {
    "name": "Mid-Air Leg Cross Hold",
    "input": "AIin rage 1+3 / AIin rage f+1+3",
    "hit_level": "t(a)",
    "damage": "30",
    "startup": "i12~14 / i15~17",
    "block": "",
    "hit": "+0d",
    "counter": "",
    "alternateInputs": [
      "AIin rage 1+3 / AIin rage f+1+3"
    ],
    "categories": [
      "throw",
      "homing"
    ],
    "notes": [
      "Homing",
      "Cannot throw break.",
      "Input f+1+3 to increase throw range, but its startup is 3 frames slower.",
      "Opponent recovers in FDFT."
    ]
  },
  {
    "name": "Spine Cracker",
    "input": "AIin rage 2+4 / AIin rage f+2+4",
    "hit_level": "t(a)",
    "damage": "20",
    "startup": "i12~14 / i15~17",
    "block": "",
    "hit": "+40d(+35)",
    "counter": "",
    "alternateInputs": [
      "AIin rage 2+4 / AIin rage f+2+4"
    ],
    "categories": [
      "throw",
      "homing"
    ],
    "notes": [
      "Tornado",
      "Homing",
      "Cannot throw break.",
      "Input f+2+4 to increase throw range, but its startup is 3 frames slower.",
      "Opponent recovers in FUFT."
    ]
  },
  {
    "name": "Double Heel Hold (DHH)",
    "input": "AIin rage d+1+3_2+4",
    "hit_level": "t(a)",
    "damage": "15",
    "startup": "i12~13",
    "block": "",
    "hit": "-5d",
    "counter": "",
    "alternateInputs": [
      "AIin rage d+1+3_2+4"
    ],
    "categories": [
      "throw"
    ],
    "notes": [
      "Cannot throw break.",
      "Opponent recovers in FDFL."
    ]
  },
  {
    "name": "Flapjack (From DHH)",
    "input": "DHin heat 1+2,1+2",
    "hit_level": "t",
    "damage": "15",
    "startup": "i12~13",
    "block": "-6",
    "hit": "-3d",
    "counter": "",
    "alternateInputs": [
      "DHin heat 1+2,1+2"
    ],
    "categories": [
      "throw"
    ],
    "notes": [
      "1 throw break.",
      "Opponent recovers in FDFT."
    ]
  },
  {
    "name": "Giant Swing (From DHH)",
    "input": "DHin heat 2,1,3,4",
    "hit_level": "t",
    "damage": "12,13 / 32",
    "startup": "i12~13",
    "block": "-6",
    "hit": "-7d(-40)",
    "counter": "",
    "alternateInputs": [
      "DHin heat 2,1,3,4"
    ],
    "categories": [
      "throw"
    ],
    "notes": [
      "2 throw break.",
      "Mash 1/2/3/4 to roll in midscreen to reduce damage, on wall splat damage is 32.",
      "Opponent recovers in FUFT if fails to roll."
    ]
  },
  {
    "name": "Running Jaguar Bomb",
    "input": "AIin rage f,f,F+2+4",
    "hit_level": "t(a)",
    "damage": "65(70)",
    "startup": "i10",
    "block": "",
    "hit": "+4d",
    "counter": "",
    "alternateInputs": [
      "AIin rage f,f,F+2+4"
    ],
    "categories": [
      "throw"
    ],
    "notes": [
      "Floor Break",
      "Cannot throw break.",
      "Input quickly to \"blue spark\" (+5 damage).",
      "Partially restores remaining Heat time.",
      "Opponent recovers in FUFT."
    ]
  },
  {
    "name": "Aerial Jaguar Bomb",
    "input": "AIin rage f,hcf+1_2",
    "hit_level": "t(a)",
    "damage": "55(60)",
    "startup": "i10 / i12~14",
    "block": "",
    "hit": "+3d",
    "counter": "",
    "alternateInputs": [
      "AIin rage f,hcf+1_2"
    ],
    "categories": [
      "throw"
    ],
    "notes": [
      "Floor Break",
      "Cannot throw break.",
      "Also by JGR.1+3 against airborne opponent.",
      "Input quickly to \"blue spark\" (+5 damage).",
      "Partially restores remaining Heat time.",
      "Opponent recovers in FUFT."
    ]
  },
  {
    "name": "Shining Torpedo",
    "input": "WALL f,hcf+1 / WALL f,f,F+2+4",
    "hit_level": "t(w)",
    "damage": "65(70)",
    "startup": "i10",
    "block": "",
    "hit": "-5d",
    "counter": "",
    "alternateInputs": [
      "WALL f,hcf+1 / WALL f,f,F+2+4"
    ],
    "categories": [
      "throw"
    ],
    "notes": [
      "Cannot throw break. Also converts from RKO.",
      "Input quickly to \"blue spark\" (+5 damage).",
      "Partially restores remaining Heat time.",
      "Opponent recovers in FUFR."
    ]
  },
  {
    "name": "Reverse Arm Slam (RAS1)",
    "input": "df+1+3",
    "hit_level": "t",
    "damage": "19",
    "startup": "i32",
    "block": "-2",
    "hit": "+1d",
    "counter": "",
    "alternateInputs": [
      "df+1+3"
    ],
    "categories": [
      "throw",
      "homing"
    ],
    "notes": [
      "Homing",
      "1 throw break. Side Switch.",
      "Very slow crouch dash then grab.",
      "Opponent recovers in FUFA."
    ]
  },
  {
    "name": "Backdrop (RAS2)",
    "input": "RAS1 1_2",
    "hit_level": "t",
    "damage": "7/15",
    "startup": "i32",
    "block": "",
    "hit": "+0d",
    "counter": "",
    "alternateInputs": [
      "RAS1 1_2"
    ],
    "categories": [
      "throw"
    ],
    "notes": [
      "Cannot throw break.",
      "Input with 2,1,1+2 for more damage.",
      "Opponent recovers in FUFR."
    ]
  },
  {
    "name": "German Suplex (RAS3)",
    "input": "RAS2 1_2",
    "hit_level": "t",
    "damage": "7/15",
    "startup": "i32",
    "block": "-9",
    "hit": "+0d",
    "counter": "",
    "alternateInputs": [
      "RAS2 1_2"
    ],
    "categories": [
      "throw"
    ],
    "notes": [
      "1 or 2 throw break, depending on King's input.",
      "Input with 3+4,1 or 3+4,2 for more damage.",
      "Opponent recovers in FUFR."
    ]
  },
  {
    "name": "Power Bomb (RAS4)",
    "input": "RAS3 1_2",
    "hit_level": "t",
    "damage": "12/17",
    "startup": "i32",
    "block": "",
    "hit": "+1d",
    "counter": "",
    "alternateInputs": [
      "RAS3 1_2"
    ],
    "categories": [
      "throw"
    ],
    "notes": [
      "Cannot throw break.",
      "Input with 1,2,3+4 for more damage.",
      "Opponent recovers in FUFT."
    ]
  },
  {
    "name": "Giant Swing (RAS5a)",
    "input": "RAS4 1",
    "hit_level": "t",
    "damage": "15/20/31",
    "startup": "i32",
    "block": "-3",
    "hit": "+1d",
    "counter": "",
    "alternateInputs": [
      "RAS4 1"
    ],
    "categories": [
      "throw"
    ],
    "notes": [
      "1 throw break. Side Switch.",
      "Input with 2,1,3,4 for more damage.",
      "On wall splat damage is 31.",
      "Opponent recovers in FUFT. Max damage 97."
    ]
  },
  {
    "name": "Muscle Buster (RAS5b)",
    "input": "RAS4 2",
    "hit_level": "t",
    "damage": "20/25",
    "startup": "i32",
    "block": "-6",
    "hit": "+1d",
    "counter": "",
    "alternateInputs": [
      "RAS4 2"
    ],
    "categories": [
      "throw"
    ],
    "notes": [
      "2 throw break. Side Switch.",
      "Input with 3,1,2,3+4,1+2 for more damage.",
      "King recovers in backturn stance.",
      "Opponent recovers in FUFA. Max damage 91."
    ]
  },
  {
    "name": "Reverse Special Stretch Bomb (RSSB1)",
    "input": "df+2+4",
    "hit_level": "t",
    "damage": "20",
    "startup": "i32",
    "block": "-2",
    "hit": "+1d",
    "counter": "",
    "alternateInputs": [
      "df+2+4"
    ],
    "categories": [
      "throw",
      "homing"
    ],
    "notes": [
      "Homing",
      "2 throw break. Side Switch.",
      "Very slow crouch dash then grab.",
      "Opponent recovers in FUFT."
    ]
  },
  {
    "name": "Cannonball Buster (RSSB2)",
    "input": "RSSB1 1_2",
    "hit_level": "t",
    "damage": "7/15",
    "startup": "i13",
    "block": "",
    "hit": "+1d",
    "counter": "",
    "alternateInputs": [
      "RSSB1 1_2"
    ],
    "categories": [
      "throw"
    ],
    "notes": [
      "Cannot throw break.",
      "Input with 2,2,1+2 for more damage.",
      "Opponent recovers in FUFT."
    ]
  },
  {
    "name": "Manhattan Drop (RSSB3)",
    "input": "RSSB2 1_2",
    "hit_level": "t",
    "damage": "7/15",
    "startup": "i13",
    "block": "-3",
    "hit": "+0d",
    "counter": "",
    "alternateInputs": [
      "RSSB2 1_2"
    ],
    "categories": [
      "throw"
    ],
    "notes": [
      "1 or 2 throw break, depending on King's input.",
      "Input with 3+4,1 or 3+4,2 for more damage.",
      "Opponent recovers in FDFA."
    ]
  },
  {
    "name": "Victory Bomb (RSSB4)",
    "input": "RSSB3 1_2",
    "hit_level": "t",
    "damage": "9/13",
    "startup": "i13",
    "block": "",
    "hit": "+1d",
    "counter": "",
    "alternateInputs": [
      "RSSB3 1_2"
    ],
    "categories": [
      "throw"
    ],
    "notes": [
      "Cannot throw break.",
      "Input with 1,2,3+4,1+2 for more damage.",
      "Opponent recovers in FUFT."
    ]
  },
  {
    "name": "Giant Swing (RSSB5a)",
    "input": "RSSB4 1",
    "hit_level": "t",
    "damage": "15/20/31",
    "startup": "i13",
    "block": "",
    "hit": "+1d",
    "counter": "",
    "alternateInputs": [
      "RSSB4 1"
    ],
    "categories": [
      "throw"
    ],
    "notes": [
      "1 throw break. Side Switch.",
      "Input with 2,1,3,4 for more damage.",
      "Opponent recovers in FUFT. Max damage 94."
    ]
  },
  {
    "name": "Muscle Buster (RSSB5b)",
    "input": "RSSB4 2",
    "hit_level": "t",
    "damage": "20/25",
    "startup": "i13",
    "block": "",
    "hit": "+1d",
    "counter": "",
    "alternateInputs": [
      "RSSB4 2"
    ],
    "categories": [
      "throw"
    ],
    "notes": [
      "2 throw break.",
      "Input with 3,1,2,3+4,1+2 for more damage.",
      "King recovers in backturn stance.",
      "Opponent recovers in FUFA. Max damage 88."
    ]
  },
  {
    "name": "Standing Heel Hold (SHH1)",
    "input": "CD 2+3",
    "hit_level": "t",
    "damage": "25",
    "startup": "i12",
    "block": "-2",
    "hit": "+0d",
    "counter": "",
    "alternateInputs": [
      "CD 2+3"
    ],
    "categories": [
      "throw"
    ],
    "notes": [
      "2 throw break.",
      "Opponent recovers in FDFR."
    ]
  },
  {
    "name": "S.T.F. (SHH2a)",
    "input": "SHH1 1,2,1+2",
    "hit_level": "t",
    "damage": "25",
    "startup": "i12",
    "block": "-10",
    "hit": "+0d",
    "counter": "",
    "alternateInputs": [
      "SHH1 1,2,1+2"
    ],
    "categories": [
      "throw"
    ],
    "notes": [
      "1 throw break. Side Switch.",
      "King suffers 10 recoverable damage on successful throw break",
      "Opponent recovers in FDFR. Max damage 50."
    ]
  },
  {
    "name": "Scorpion Death Lock (SHH2b)",
    "input": "SHH1 2,1,1+3",
    "hit_level": "t",
    "damage": "30",
    "startup": "i12",
    "block": "-10",
    "hit": "+0d",
    "counter": "",
    "alternateInputs": [
      "SHH1 2,1,1+3"
    ],
    "categories": [
      "throw"
    ],
    "notes": [
      "2 throw break.",
      "King suffers 10 recoverable damage on successful throw break",
      "Opponent recovers in FDFR. Max damage 55."
    ]
  },
  {
    "name": "Indian Death Lock (SHH2c)",
    "input": "SHH1 1+2,1,3",
    "hit_level": "t",
    "damage": "20",
    "startup": "i12",
    "block": "-10",
    "hit": "+0d",
    "counter": "",
    "alternateInputs": [
      "SHH1 1+2,1,3"
    ],
    "categories": [
      "throw"
    ],
    "notes": [
      "1+2 throw break.",
      "King suffers 10 recoverable damage on successful throw break",
      "Opponent recovers in FDFL."
    ]
  },
  {
    "name": "King's Bridge (SHH3ca)",
    "input": "SHH2c 3,4,1+2,3+4",
    "hit_level": "t",
    "damage": "40",
    "startup": "i12",
    "block": "",
    "hit": "+0d",
    "counter": "",
    "alternateInputs": [
      "SHH2c 3,4,1+2,3+4"
    ],
    "categories": [
      "throw"
    ],
    "notes": [
      "Cannot throw break.",
      "Opponent recovers in FDFT. Max Damage 85."
    ]
  },
  {
    "name": "Arm Breaker (AB1)",
    "input": "CD 1+4",
    "hit_level": "t",
    "damage": "20",
    "startup": "i12",
    "block": "-2",
    "hit": "+1d",
    "counter": "",
    "alternateInputs": [
      "CD 1+4"
    ],
    "categories": [
      "throw"
    ],
    "notes": [
      "1 Throw break.",
      "Opponent recovers in FUFT."
    ]
  },
  {
    "name": "Triple Arm Breaker (AB2a)",
    "input": "AB1 1,1+2",
    "hit_level": "t",
    "damage": "12,18",
    "startup": "i12",
    "block": "-3",
    "hit": "+2d",
    "counter": "",
    "alternateInputs": [
      "AB1 1,1+2"
    ],
    "categories": [
      "throw"
    ],
    "notes": [
      "1 throw break.",
      "Opponent recovers in FUFT. Max damage 50."
    ]
  },
  {
    "name": "Head Jammer (AB2b)",
    "input": "AB1 2,4,2+4",
    "hit_level": "t",
    "damage": "20",
    "startup": "i12",
    "block": "-3",
    "hit": "+1d",
    "counter": "",
    "alternateInputs": [
      "AB1 2,4,2+4"
    ],
    "categories": [
      "throw"
    ],
    "notes": [
      "2 throw break.",
      "Opponent recovers in FUFL."
    ]
  },
  {
    "name": "Struggle Combination (AB2b1)",
    "input": "AB2b 3,4,3+4,1+2",
    "hit_level": "t",
    "damage": "20",
    "startup": "i12",
    "block": "",
    "hit": "+1d",
    "counter": "",
    "alternateInputs": [
      "AB2b 3,4,3+4,1+2"
    ],
    "categories": [
      "throw"
    ],
    "notes": [
      "Cannot throw break.",
      "Opponent recovers in FUFR. Max Damage 60."
    ]
  },
  {
    "name": "Chicken Wing Face Lock (AB2c)",
    "input": "AB1 2,1,1+3",
    "hit_level": "t",
    "damage": "20",
    "startup": "i12",
    "block": "-3",
    "hit": "+0d",
    "counter": "",
    "alternateInputs": [
      "AB1 2,1,1+3"
    ],
    "categories": [
      "throw"
    ],
    "notes": [
      "1+2 throw break.",
      "Opponent recovers in FDFT."
    ]
  },
  {
    "name": "Dragon Sleeper Finish (AB3ca)",
    "input": "AB2c 2,1,3,1+2",
    "hit_level": "t",
    "damage": "25",
    "startup": "i12",
    "block": "-3",
    "hit": "+1d",
    "counter": "",
    "alternateInputs": [
      "AB2c 2,1,3,1+2"
    ],
    "categories": [
      "throw"
    ],
    "notes": [
      "1 throw break.",
      "Opponent recovers in FUFA. Max damage 65."
    ]
  },
  {
    "name": "Rolling Death Cradle (AB3cb)",
    "input": "AB2c 1,3,4,2,1+2",
    "hit_level": "t",
    "damage": "60",
    "startup": "i12",
    "block": "-3",
    "hit": "+1d",
    "counter": "",
    "alternateInputs": [
      "AB2c 1,3,4,2,1+2"
    ],
    "categories": [
      "throw"
    ],
    "notes": [
      "2 throw break.",
      "Opponent recovers in FUFL. Max damage 100."
    ]
  },
  {
    "name": "Cobra Clutch (MMD1)",
    "input": "JGS 1+4_2+3",
    "hit_level": "t",
    "damage": "20",
    "startup": "i12",
    "block": "-3",
    "hit": "+0d",
    "counter": "",
    "alternateInputs": [
      "JGS 1+4_2+3"
    ],
    "categories": [
      "throw",
      "homing"
    ],
    "notes": [
      "Homing",
      "1 or 2 throw break, depending on King's input.",
      "Opponent recovers in FDFT.",
      "Becomes f,hcf+1 / 2+4 on air grab / wall splat."
    ]
  },
  {
    "name": "Cobra Twist (MMD2)",
    "input": "MMD1 1,4,2,3",
    "hit_level": "t",
    "damage": "12",
    "startup": "i12",
    "block": "",
    "hit": "+1d",
    "counter": "",
    "alternateInputs": [
      "MMD1 1,4,2,3"
    ],
    "categories": [
      "throw"
    ],
    "notes": [
      "Cannot throw break.",
      "Opponent recovers in FUFL."
    ]
  },
  {
    "name": "Reverse DDT (MMD3)",
    "input": "MMD2 1,1+3/ MMD2 2,2+4",
    "hit_level": "t",
    "damage": "13",
    "startup": "i12",
    "block": "-6",
    "hit": "+0d",
    "counter": "",
    "alternateInputs": [
      "MMD2 1,1+3/ MMD2 2,2+4"
    ],
    "categories": [
      "throw"
    ],
    "notes": [
      "1 or 2 throw break, depending on King's input.",
      "Opponent recovers in FDFA."
    ]
  },
  {
    "name": "Reverse Special Stretch Bomb (MMD4)",
    "input": "MMD3 1+2,1,1+3/ MMD3 1+2,2,2+4",
    "hit_level": "t",
    "damage": "12",
    "startup": "i12",
    "block": "-6",
    "hit": "+1d",
    "counter": "",
    "alternateInputs": [
      "MMD3 1+2,1,1+3/ MMD3 1+2,2,2+4"
    ],
    "categories": [
      "throw"
    ],
    "notes": [
      "1 or 2 throw break, depending on King's input.",
      "Opponent recovers in FUFA."
    ]
  },
  {
    "name": "Samurai Rock (MMD4a)",
    "input": "MMD3 2,3,1,1+2",
    "hit_level": "t",
    "damage": "24",
    "startup": "i12",
    "block": "-6",
    "hit": "+0d",
    "counter": "",
    "alternateInputs": [
      "MMD3 2,3,1,1+2"
    ],
    "categories": [
      "throw"
    ],
    "notes": [
      "1+2 Throw break.",
      "Opponent recovers in FDFR. Max Damage 69."
    ]
  },
  {
    "name": "Backdrop (MMD5)",
    "input": "MMD4 3+4,1+2",
    "hit_level": "t",
    "damage": "10",
    "startup": "i12",
    "block": "",
    "hit": "+0d",
    "counter": "",
    "alternateInputs": [
      "MMD4 3+4,1+2"
    ],
    "categories": [
      "throw"
    ],
    "notes": [
      "Cannot throw break.",
      "Opponent recovers in FDFA."
    ]
  },
  {
    "name": "Sol Naciente (MMD6a)",
    "input": "MMD5 1+2,4,2,1+2",
    "hit_level": "t",
    "damage": "11,15",
    "startup": "i12",
    "block": "-3",
    "hit": "+0d",
    "counter": "",
    "alternateInputs": [
      "MMD5 1+2,4,2,1+2"
    ],
    "categories": [
      "throw"
    ],
    "notes": [
      "1+2 throw break.",
      "Opponent recovers in FDFL. Max Damage 93."
    ]
  },
  {
    "name": "Burning Hammer (MMD6)",
    "input": "MMD5 1+2,3,1+3/ MMD5 1+2,4,2+4",
    "hit_level": "t",
    "damage": "18",
    "startup": "i12",
    "block": "-3",
    "hit": "+0d",
    "counter": "",
    "alternateInputs": [
      "MMD5 1+2,3,1+3/ MMD5 1+2,4,2+4"
    ],
    "categories": [
      "throw"
    ],
    "notes": [
      "1 or 2 throw break, depending on King's input.",
      "Opponent recovers in FDFA."
    ]
  },
  {
    "name": "Screwdriver (MMD7)",
    "input": "MMD6 2,4,1,1+3/ MMD6 2,4,1,2+4",
    "hit_level": "t",
    "damage": "31",
    "startup": "i12",
    "block": "-6",
    "hit": "-10d",
    "counter": "",
    "alternateInputs": [
      "MMD6 2,4,1,1+3/ MMD6 2,4,1,2+4"
    ],
    "categories": [
      "throw"
    ],
    "notes": [
      "1 or 2 throw break, depending on King's input.",
      "Opponent recovers in FUFA. Max Damage 116."
    ]
  }
]
